{
  "book": "Hebrews",
  "chapter": 3,
  "data": [
    {
      "v": 1
    },
    {
      "txt": "Ὅθεν,",
      "lem": "ὅθεν",
      "prs": "conj"
    },
    {
      "txt": "ἀδελφοὶ",
      "lem": "ἀδελφός",
      "prs": "noun voc pl masc",
      "stm": "ἀδελφ",
      "suf": "οὶ",
      "cs": "v",
      "segs": [
        {
          "t": "ἀδελφ",
          "ch": {
            "morph": "stm"
          }
        },
        {
          "t": "οὶ",
          "ch": {
            "morph": "suf",
            "case": "v"
          }
        }
      ]
    },
    {
      "txt": "ἅγιοι,",
      "lem": "ἅγιος",
      "prs": "adj voc pl masc",
      "stm": "ἅγι",
      "suf": "οι",
      "cs": "v",
      "segs": [
        {
          "t": "ἅγι",
          "ch": {
            "morph": "stm"
          }
        },
        {
          "t": "οι",
          "ch": {
            "morph": "suf",
            "case": "v"
          }
        }
      ]
    },
    {
      "txt": "κλήσεως",
      "lem": "κλῆσις",
      "prs": "noun gen sg fem",
      "stm": "κλήσ",
      "suf": "εως",
      "cs": "g",
      "segs": [
        {
          "t": "κλήσ",
          "ch": {
            "morph": "stm"
          }
        },
        {
          "t": "εως",
          "ch": {
            "morph": "suf",
            "case": "g"
          }
        }
      ]
    },
    {
      "txt": "ἐπουρανίου",
      "lem": "ἐπουράνιος",
      "prs": "adj gen sg fem",
      "stm": "ἐπουρανί",
      "suf": "ου",
      "cs": "g",
      "segs": [
        {
          "t": "ἐπουρανί",
          "ch": {
            "morph": "stm"
          }
        },
        {
          "t": "ου",
          "ch": {
            "morph": "suf",
            "case": "g"
          }
        }
      ]
    },
    {
      "txt": "μέτοχοι,",
      "lem": "μέτοχος",
      "prs": "adj voc pl masc",
      "stm": "μέτοχ",
      "suf": "οι",
      "cs": "v",
      "segs": [
        {
          "t": "μέτοχ",
          "ch": {
            "morph": "stm"
          }
        },
        {
          "t": "οι",
          "ch": {
            "morph": "suf",
            "case": "v"
          }
        }
      ]
    },
    {
      "br": true
    },
    {
      "txt": "κατανοήσατε",
      "lem": "κατανοέω",
      "prs": "aor act imp 2 pl",
      "pfx": "κατα",
      "stm": "νοή",
      "frm": "σα",
      "ve": "τε",
      "segs": [
        {
          "t": "κατα",
          "ch": {
            "morph": "pfx"
          }
        },
        {
          "t": "νοή",
          "ch": {
            "morph": "stm"
          }
        },
        {
          "t": "σα",
          "ch": {
            "morph": "frm"
          }
        },
        {
          "t": "τε",
          "ch": {
            "morph": "ve"
          }
        }
      ],
      "tvm": "AAD"
    },
    {
      "txt": "τὸν",
      "lem": "ὁ",
      "prs": "art acc sg masc",
      "stm": "τὸν",
      "cs": "a",
      "segs": [
        {
          "t": "τὸν",
          "ch": {
            "morph": "suf",
            "case": "a"
          }
        }
      ]
    },
    {
      "txt": "ἀπόστολον",
      "lem": "ἀπόστολος",
      "prs": "noun acc sg masc",
      "stm": "ἀπόστολ",
      "suf": "ον",
      "cs": "a",
      "segs": [
        {
          "t": "ἀπόστολ",
          "ch": {
            "morph": "stm"
          }
        },
        {
          "t": "ον",
          "ch": {
            "morph": "suf",
            "case": "a"
          }
        }
      ]
    },
    {
      "txt": "καὶ",
      "lem": "καί",
      "prs": "conj"
    },
    {
      "txt": "ἀρχιερέα",
      "lem": "ἀρχιερεύς",
      "prs": "noun acc sg masc",
      "stm": "ἀρχιερ",
      "suf": "έα",
      "cs": "a",
      "segs": [
        {
          "t": "ἀρχιερ",
          "ch": {
            "morph": "stm"
          }
        },
        {
          "t": "έα",
          "ch": {
            "morph": "suf",
            "case": "a"
          }
        }
      ]
    },
    {
      "txt": "τῆς",
      "lem": "ὁ",
      "prs": "art gen sg fem",
      "stm": "τῆς",
      "cs": "g",
      "segs": [
        {
          "t": "τῆς",
          "ch": {
            "morph": "suf",
            "case": "g"
          }
        }
      ]
    },
    {
      "txt": "ὁμολογίας",
      "lem": "ὁμολογία",
      "prs": "noun gen sg fem",
      "stm": "ὁμολογί",
      "suf": "ας",
      "cs": "g",
      "segs": [
        {
          "t": "ὁμολογί",
          "ch": {
            "morph": "stm"
          }
        },
        {
          "t": "ας",
          "ch": {
            "morph": "suf",
            "case": "g"
          }
        }
      ]
    },
    {
      "txt": "ἡμῶν",
      "lem": "ἐγώ",
      "prs": "pers.pron gen pl",
      "stm": "ἡμ",
      "suf": "ῶν",
      "cs": "g",
      "segs": [
        {
          "t": "ἡμ",
          "ch": {
            "morph": "stm"
          }
        },
        {
          "t": "ῶν",
          "ch": {
            "morph": "suf",
            "case": "g"
          }
        }
      ]
    },
    {
      "txt": "Ἰησοῦν,",
      "lem": "Ἰησοῦς",
      "prs": "noun acc sg masc",
      "stm": "Ἰησο",
      "suf": "ῦν",
      "cs": "a",
      "segs": [
        {
          "t": "Ἰησο",
          "ch": {
            "morph": "stm"
          }
        },
        {
          "t": "ῦν",
          "ch": {
            "morph": "suf",
            "case": "a"
          }
        }
      ]
    },
    {
      "br": true
    },
    {
      "v": 2
    },
    {
      "txt": "πιστὸν",
      "lem": "πιστός",
      "prs": "adj acc sg masc",
      "stm": "πιστ",
      "suf": "ὸν",
      "cs": "a",
      "segs": [
        {
          "t": "πιστ",
          "ch": {
            "morph": "stm"
          }
        },
        {
          "t": "ὸν",
          "ch": {
            "morph": "suf",
            "case": "a"
          }
        }
      ]
    },
    {
      "txt": "ὄντα",
      "lem": "εἰμί",
      "prs": "pres act ptc acc sg masc",
      "ptc": "ὄντ",
      "suf": "α",
      "cs": "a",
      "segs": [
        {
          "t": "ὄντ",
          "ch": {
            "morph": "pmk",
            "ptc": "marker"
          }
        },
        {
          "t": "α",
          "ch": {
            "morph": "suf",
            "ptc": "marker",
            "case": "a"
          }
        }
      ],
      "tvm": "PAP",
      "igl": "being"
    },
    {
      "txt": "τῷ",
      "lem": "ὁ",
      "prs": "art dat sg masc",
      "stm": "τῷ",
      "cs": "d",
      "segs": [
        {
          "t": "τῷ",
          "ch": {
            "morph": "suf",
            "case": "d"
          }
        }
      ]
    },
    {
      "txt": "ποιήσαντι",
      "lem": "ποιέω",
      "prs": "aor act ptc dat sg masc",
      "stm": "ποιή",
      "frm": "σα",
      "ptc": "ντ",
      "suf": "ι",
      "cs": "d",
      "segs": [
        {
          "t": "ποιή",
          "ch": {
            "morph": "stm"
          }
        },
        {
          "t": "σα",
          "ch": {
            "morph": "frm",
            "ptc": "marker"
          }
        },
        {
          "t": "ντ",
          "ch": {
            "morph": "pmk",
            "ptc": "marker"
          }
        },
        {
          "t": "ι",
          "ch": {
            "morph": "suf",
            "ptc": "marker",
            "case": "d"
          }
        }
      ],
      "tvm": "AAP"
    },
    {
      "txt": "αὐτὸν",
      "lem": "αὐτός",
      "prs": "pers.pron acc sg masc",
      "stm": "αὐτ",
      "suf": "ὸν",
      "cs": "a",
      "segs": [
        {
          "t": "αὐτ",
          "ch": {
            "morph": "stm"
          }
        },
        {
          "t": "ὸν",
          "ch": {
            "morph": "suf",
            "case": "a"
          }
        }
      ]
    },
    {
      "br": true
    },
    {
      "txt": "ὡς",
      "lem": "ὡς",
      "prs": "conj"
    },
    {
      "txt": "καὶ",
      "lem": "καί",
      "prs": "adv"
    },
    {
      "txt": "Μωϋσῆς",
      "lem": "Μωϋσῆς",
      "prs": "noun nom sg masc",
      "stm": "Μωϋσ",
      "suf": "ῆς",
      "cs": "n",
      "segs": [
        {
          "t": "Μωϋσ",
          "ch": {
            "morph": "stm"
          }
        },
        {
          "t": "ῆς",
          "ch": {
            "morph": "suf",
            "case": "n"
          }
        }
      ]
    },
    {
      "txt": "ἐν",
      "lem": "ἐν",
      "prs": "prep"
    },
    {
      "txt": "τῷ",
      "lem": "ὁ",
      "prs": "art dat sg masc",
      "stm": "τῷ",
      "cs": "d",
      "segs": [
        {
          "t": "τῷ",
          "ch": {
            "morph": "suf",
            "case": "d"
          }
        }
      ]
    },
    {
      "txt": "οἴκῳ",
      "lem": "οἶκος",
      "prs": "noun dat sg masc",
      "stm": "οἴκ",
      "suf": "ῳ",
      "cs": "d",
      "segs": [
        {
          "t": "οἴκ",
          "ch": {
            "morph": "stm"
          }
        },
        {
          "t": "ῳ",
          "ch": {
            "morph": "suf",
            "case": "d"
          }
        }
      ]
    },
    {
      "txt": "αὐτοῦ.",
      "lem": "αὐτός",
      "prs": "pers.pron gen sg masc",
      "stm": "αὐτ",
      "suf": "οῦ",
      "cs": "g",
      "segs": [
        {
          "t": "αὐτ",
          "ch": {
            "morph": "stm"
          }
        },
        {
          "t": "οῦ",
          "ch": {
            "morph": "suf",
            "case": "g"
          }
        }
      ]
    },
    {
      "br": true
    },
    {
      "v": 3
    },
    {
      "txt": "πλείονος",
      "lem": "πολύς",
      "prs": "adj gen sg fem",
      "stm": "πλείον",
      "suf": "ος",
      "cs": "g",
      "segs": [
        {
          "t": "πλείον",
          "ch": {
            "morph": "stm"
          }
        },
        {
          "t": "ος",
          "ch": {
            "morph": "suf",
            "case": "g"
          }
        }
      ]
    },
    {
      "txt": "γὰρ",
      "lem": "γάρ",
      "prs": "conj"
    },
    {
      "txt": "οὗτος",
      "lem": "οὗτος",
      "prs": "dem.pron nom sg masc",
      "stm": "οὗτ",
      "suf": "ος",
      "cs": "n",
      "segs": [
        {
          "t": "οὗτ",
          "ch": {
            "morph": "stm"
          }
        },
        {
          "t": "ος",
          "ch": {
            "morph": "suf",
            "case": "n"
          }
        }
      ]
    },
    {
      "txt": "δόξης",
      "lem": "δόξα",
      "prs": "noun gen sg fem",
      "stm": "δόξ",
      "suf": "ης",
      "cs": "g",
      "segs": [
        {
          "t": "δόξ",
          "ch": {
            "morph": "stm"
          }
        },
        {
          "t": "ης",
          "ch": {
            "morph": "suf",
            "case": "g"
          }
        }
      ]
    },
    {
      "txt": "παρὰ",
      "lem": "παρά",
      "prs": "prep"
    },
    {
      "txt": "Μωϋσῆν",
      "lem": "Μωϋσῆς",
      "prs": "noun acc sg masc",
      "stm": "Μωϋσ",
      "suf": "ῆν",
      "cs": "a",
      "segs": [
        {
          "t": "Μωϋσ",
          "ch": {
            "morph": "stm"
          }
        },
        {
          "t": "ῆν",
          "ch": {
            "morph": "suf",
            "case": "a"
          }
        }
      ]
    },
    {
      "txt": "ἠξίωται",
      "lem": "ἀξιόω",
      "prs": "perf pass ind 3 sg",
      "stm": "ἠξίω",
      "ve": "ται",
      "segs": [
        {
          "t": "ἠξίω",
          "ch": {
            "morph": "stm"
          }
        },
        {
          "t": "ται",
          "ch": {
            "morph": "ve"
          }
        }
      ],
      "tvm": "XPI",
      "igl": "been considered worthy"
    },
    {
      "br": true
    },
    {
      "txt": "καθʼ",
      "lem": "κατά",
      "prs": "prep"
    },
    {
      "txt": "ὅσον",
      "lem": "ὅσος",
      "prs": "rel.pron acc sg neut",
      "stm": "ὅσ",
      "suf": "ον",
      "cs": "a",
      "segs": [
        {
          "t": "ὅσ",
          "ch": {
            "morph": "stm"
          }
        },
        {
          "t": "ον",
          "ch": {
            "morph": "suf",
            "case": "a"
          }
        }
      ]
    },
    {
      "txt": "πλείονα",
      "lem": "πολύς",
      "prs": "adj acc sg fem",
      "stm": "πλείον",
      "suf": "α",
      "cs": "a",
      "segs": [
        {
          "t": "πλείον",
          "ch": {
            "morph": "stm"
          }
        },
        {
          "t": "α",
          "ch": {
            "morph": "suf",
            "case": "a"
          }
        }
      ]
    },
    {
      "txt": "τιμὴν",
      "lem": "τιμή",
      "prs": "noun acc sg fem",
      "stm": "τιμ",
      "suf": "ὴν",
      "cs": "a",
      "segs": [
        {
          "t": "τιμ",
          "ch": {
            "morph": "stm"
          }
        },
        {
          "t": "ὴν",
          "ch": {
            "morph": "suf",
            "case": "a"
          }
        }
      ]
    },
    {
      "txt": "ἔχει",
      "lem": "ἔχω",
      "prs": "pres act ind 3 sg",
      "stm": "ἔχ",
      "ve": "ει",
      "segs": [
        {
          "t": "ἔχ",
          "ch": {
            "morph": "stm"
          }
        },
        {
          "t": "ει",
          "ch": {
            "morph": "ve"
          }
        }
      ],
      "tvm": "PAI"
    },
    {
      "txt": "τοῦ",
      "lem": "ὁ",
      "prs": "art gen sg masc",
      "stm": "τοῦ",
      "cs": "g",
      "segs": [
        {
          "t": "τοῦ",
          "ch": {
            "morph": "suf",
            "case": "g"
          }
        }
      ]
    },
    {
      "txt": "οἴκου",
      "lem": "οἶκος",
      "prs": "noun gen sg masc",
      "stm": "οἴκ",
      "suf": "ου",
      "cs": "g",
      "segs": [
        {
          "t": "οἴκ",
          "ch": {
            "morph": "stm"
          }
        },
        {
          "t": "ου",
          "ch": {
            "morph": "suf",
            "case": "g"
          }
        }
      ]
    },
    {
      "txt": "ὁ",
      "lem": "ὁ",
      "prs": "art nom sg masc",
      "stm": "ὁ",
      "cs": "n",
      "segs": [
        {
          "t": "ὁ",
          "ch": {
            "morph": "suf",
            "case": "n"
          }
        }
      ]
    },
    {
      "txt": "κατασκευάσας",
      "lem": "κατασκευάζω",
      "prs": "aor act ptc nom sg masc",
      "pfx": "κατα",
      "stm": "σκευά",
      "frm": "σα",
      "ptc": "ς",
      "cs": "n",
      "segs": [
        {
          "t": "κατα",
          "ch": {
            "morph": "pfx"
          }
        },
        {
          "t": "σκευά",
          "ch": {
            "morph": "stm"
          }
        },
        {
          "t": "σα",
          "ch": {
            "morph": "frm",
            "ptc": "marker"
          }
        },
        {
          "t": "ς",
          "ch": {
            "morph": "pmk",
            "ptc": "marker"
          }
        }
      ],
      "tvm": "AAP"
    },
    {
      "txt": "αὐτόν·",
      "lem": "αὐτός",
      "prs": "pers.pron acc sg masc",
      "stm": "αὐτ",
      "suf": "όν",
      "cs": "a",
      "segs": [
        {
          "t": "αὐτ",
          "ch": {
            "morph": "stm"
          }
        },
        {
          "t": "όν",
          "ch": {
            "morph": "suf",
            "case": "a"
          }
        }
      ]
    },
    {
      "br": true
    },
    {
      "v": 4
    },
    {
      "txt": "πᾶς",
      "lem": "πᾶς",
      "prs": "adj nom sg masc",
      "stm": "π",
      "suf": "ᾶς",
      "cs": "n",
      "segs": [
        {
          "t": "π",
          "ch": {
            "morph": "stm"
          }
        },
        {
          "t": "ᾶς",
          "ch": {
            "morph": "suf",
            "case": "n"
          }
        }
      ]
    },
    {
      "txt": "γὰρ",
      "lem": "γάρ",
      "prs": "conj"
    },
    {
      "txt": "οἶκος",
      "lem": "οἶκος",
      "prs": "noun nom sg masc",
      "stm": "οἶκ",
      "suf": "ος",
      "cs": "n",
      "segs": [
        {
          "t": "οἶκ",
          "ch": {
            "morph": "stm"
          }
        },
        {
          "t": "ος",
          "ch": {
            "morph": "suf",
            "case": "n"
          }
        }
      ]
    },
    {
      "txt": "κατασκευάζεται",
      "lem": "κατασκευάζω",
      "prs": "pres pass ind 3 sg",
      "pfx": "κατα",
      "stm": "σκευάζ",
      "ve": "εται",
      "segs": [
        {
          "t": "κατα",
          "ch": {
            "morph": "pfx"
          }
        },
        {
          "t": "σκευάζ",
          "ch": {
            "morph": "stm"
          }
        },
        {
          "t": "εται",
          "ch": {
            "morph": "ve"
          }
        }
      ],
      "tvm": "PPI",
      "igl": "is built"
    },
    {
      "txt": "ὑπό",
      "lem": "ὑπό",
      "prs": "prep"
    },
    {
      "txt": "τινος,",
      "lem": "τις",
      "prs": "inter.pron gen sg masc",
      "stm": "τιν",
      "suf": "ος",
      "cs": "g",
      "segs": [
        {
          "t": "τιν",
          "ch": {
            "morph": "stm"
          }
        },
        {
          "t": "ος",
          "ch": {
            "morph": "suf",
            "case": "g"
          }
        }
      ]
    },
    {
      "br": true
    },
    {
      "txt": "ὁ",
      "lem": "ὁ",
      "prs": "art nom sg masc",
      "stm": "ὁ",
      "cs": "n",
      "segs": [
        {
          "t": "ὁ",
          "ch": {
            "morph": "suf",
            "case": "n"
          }
        }
      ]
    },
    {
      "txt": "δὲ",
      "lem": "δέ",
      "prs": "conj"
    },
    {
      "txt": "πάντα",
      "lem": "πᾶς",
      "prs": "adj acc pl neut",
      "stm": "πάντ",
      "suf": "α",
      "cs": "a",
      "segs": [
        {
          "t": "πάντ",
          "ch": {
            "morph": "stm"
          }
        },
        {
          "t": "α",
          "ch": {
            "morph": "suf",
            "case": "a"
          }
        }
      ]
    },
    {
      "txt": "κατασκευάσας",
      "lem": "κατασκευάζω",
      "prs": "aor act ptc nom sg masc",
      "pfx": "κατα",
      "stm": "σκευά",
      "frm": "σα",
      "ptc": "ς",
      "cs": "n",
      "segs": [
        {
          "t": "κατα",
          "ch": {
            "morph": "pfx"
          }
        },
        {
          "t": "σκευά",
          "ch": {
            "morph": "stm"
          }
        },
        {
          "t": "σα",
          "ch": {
            "morph": "frm",
            "ptc": "marker"
          }
        },
        {
          "t": "ς",
          "ch": {
            "morph": "pmk",
            "ptc": "marker"
          }
        }
      ],
      "tvm": "AAP"
    },
    {
      "txt": "θεός.",
      "lem": "θεός",
      "prs": "noun nom sg masc",
      "stm": "θε",
      "suf": "ός",
      "cs": "n",
      "segs": [
        {
          "t": "θε",
          "ch": {
            "morph": "stm"
          }
        },
        {
          "t": "ός",
          "ch": {
            "morph": "suf",
            "case": "n"
          }
        }
      ]
    },
    {
      "br": true
    },
    {
      "v": 5
    },
    {
      "txt": "καὶ",
      "lem": "καί",
      "prs": "conj"
    },
    {
      "txt": "Μωϋσῆς",
      "lem": "Μωϋσῆς",
      "prs": "noun nom sg masc",
      "stm": "Μωϋσ",
      "suf": "ῆς",
      "cs": "n",
      "segs": [
        {
          "t": "Μωϋσ",
          "ch": {
            "morph": "stm"
          }
        },
        {
          "t": "ῆς",
          "ch": {
            "morph": "suf",
            "case": "n"
          }
        }
      ]
    },
    {
      "txt": "μὲν",
      "lem": "μέν",
      "prs": "conj"
    },
    {
      "txt": "πιστὸς",
      "lem": "πιστός",
      "prs": "adj nom sg masc",
      "stm": "πιστ",
      "suf": "ὸς",
      "cs": "n",
      "segs": [
        {
          "t": "πιστ",
          "ch": {
            "morph": "stm"
          }
        },
        {
          "t": "ὸς",
          "ch": {
            "morph": "suf",
            "case": "n"
          }
        }
      ]
    },
    {
      "txt": "ἐν",
      "lem": "ἐν",
      "prs": "prep"
    },
    {
      "txt": "ὅλῳ",
      "lem": "ὅλος",
      "prs": "adj dat sg masc",
      "stm": "ὅλ",
      "suf": "ῳ",
      "cs": "d",
      "segs": [
        {
          "t": "ὅλ",
          "ch": {
            "morph": "stm"
          }
        },
        {
          "t": "ῳ",
          "ch": {
            "morph": "suf",
            "case": "d"
          }
        }
      ]
    },
    {
      "txt": "τῷ",
      "lem": "ὁ",
      "prs": "art dat sg masc",
      "stm": "τῷ",
      "cs": "d",
      "segs": [
        {
          "t": "τῷ",
          "ch": {
            "morph": "suf",
            "case": "d"
          }
        }
      ]
    },
    {
      "txt": "οἴκῳ",
      "lem": "οἶκος",
      "prs": "noun dat sg masc",
      "stm": "οἴκ",
      "suf": "ῳ",
      "cs": "d",
      "segs": [
        {
          "t": "οἴκ",
          "ch": {
            "morph": "stm"
          }
        },
        {
          "t": "ῳ",
          "ch": {
            "morph": "suf",
            "case": "d"
          }
        }
      ]
    },
    {
      "txt": "αὐτοῦ",
      "lem": "αὐτός",
      "prs": "pers.pron gen sg masc",
      "stm": "αὐτ",
      "suf": "οῦ",
      "cs": "g",
      "segs": [
        {
          "t": "αὐτ",
          "ch": {
            "morph": "stm"
          }
        },
        {
          "t": "οῦ",
          "ch": {
            "morph": "suf",
            "case": "g"
          }
        }
      ]
    },
    {
      "txt": "ὡς",
      "lem": "ὡς",
      "prs": "conj"
    },
    {
      "txt": "θεράπων",
      "lem": "θεράπων",
      "prs": "noun nom sg masc",
      "stm": "θεράπων",
      "segs": [
        {
          "t": "θεράπων",
          "ch": {
            "morph": "stm"
          }
        }
      ]
    },
    {
      "br": true
    },
    {
      "txt": "εἰς",
      "lem": "εἰς",
      "prs": "prep"
    },
    {
      "txt": "μαρτύριον",
      "lem": "μαρτύριον",
      "prs": "noun acc sg neut",
      "stm": "μαρτύρι",
      "suf": "ον",
      "cs": "a",
      "segs": [
        {
          "t": "μαρτύρι",
          "ch": {
            "morph": "stm"
          }
        },
        {
          "t": "ον",
          "ch": {
            "morph": "suf",
            "case": "a"
          }
        }
      ]
    },
    {
      "txt": "τῶν",
      "lem": "ὁ",
      "prs": "art gen pl neut",
      "stm": "τῶν",
      "cs": "g",
      "segs": [
        {
          "t": "τῶν",
          "ch": {
            "morph": "suf",
            "case": "g"
          }
        }
      ]
    },
    {
      "txt": "λαληθησομένων,",
      "lem": "λαλέω",
      "prs": "fut pass ptc gen pl neut",
      "stm": "λαλη",
      "frm": "θησ",
      "suf": "ομένων",
      "cs": "g",
      "segs": [
        {
          "t": "λαλη",
          "ch": {
            "morph": "stm"
          }
        },
        {
          "t": "θησ",
          "ch": {
            "morph": "frm"
          }
        },
        {
          "t": "ομένων",
          "ch": {
            "morph": "suf",
            "case": "g"
          }
        }
      ],
      "tvm": "FPP",
      "igl": "about to be spoken"
    },
    {
      "br": true
    },
    {
      "v": 6
    },
    {
      "txt": "Χριστὸς",
      "lem": "Χριστός",
      "prs": "noun nom sg masc",
      "stm": "Χριστ",
      "suf": "ὸς",
      "cs": "n",
      "segs": [
        {
          "t": "Χριστ",
          "ch": {
            "morph": "stm"
          }
        },
        {
          "t": "ὸς",
          "ch": {
            "morph": "suf",
            "case": "n"
          }
        }
      ]
    },
    {
      "txt": "δὲ",
      "lem": "δέ",
      "prs": "conj"
    },
    {
      "txt": "ὡς",
      "lem": "ὡς",
      "prs": "conj"
    },
    {
      "txt": "υἱὸς",
      "lem": "υἱός",
      "prs": "noun nom sg masc",
      "stm": "υἱ",
      "suf": "ὸς",
      "cs": "n",
      "segs": [
        {
          "t": "υἱ",
          "ch": {
            "morph": "stm"
          }
        },
        {
          "t": "ὸς",
          "ch": {
            "morph": "suf",
            "case": "n"
          }
        }
      ]
    },
    {
      "txt": "ἐπὶ",
      "lem": "ἐπί",
      "prs": "prep"
    },
    {
      "txt": "τὸν",
      "lem": "ὁ",
      "prs": "art acc sg masc",
      "stm": "τὸν",
      "cs": "a",
      "segs": [
        {
          "t": "τὸν",
          "ch": {
            "morph": "suf",
            "case": "a"
          }
        }
      ]
    },
    {
      "txt": "οἶκον",
      "lem": "οἶκος",
      "prs": "noun acc sg masc",
      "stm": "οἶκ",
      "suf": "ον",
      "cs": "a",
      "segs": [
        {
          "t": "οἶκ",
          "ch": {
            "morph": "stm"
          }
        },
        {
          "t": "ον",
          "ch": {
            "morph": "suf",
            "case": "a"
          }
        }
      ]
    },
    {
      "txt": "αὐτοῦ·",
      "lem": "αὐτός",
      "prs": "pers.pron gen sg masc",
      "stm": "αὐτ",
      "suf": "οῦ",
      "cs": "g",
      "segs": [
        {
          "t": "αὐτ",
          "ch": {
            "morph": "stm"
          }
        },
        {
          "t": "οῦ",
          "ch": {
            "morph": "suf",
            "case": "g"
          }
        }
      ]
    },
    {
      "br": true
    },
    {
      "txt": "ὃς",
      "lem": "ὅς",
      "prs": "rel.pron nom sg masc",
      "stm": "ὃ",
      "suf": "ς",
      "cs": "n",
      "segs": [
        {
          "t": "ὃ",
          "ch": {
            "morph": "stm"
          }
        },
        {
          "t": "ς",
          "ch": {
            "morph": "suf",
            "case": "n"
          }
        }
      ]
    },
    {
      "txt": "οἶκός",
      "lem": "οἶκος",
      "prs": "noun nom sg masc",
      "stm": "οἶκ",
      "suf": "ός",
      "cs": "n",
      "segs": [
        {
          "t": "οἶκ",
          "ch": {
            "morph": "stm"
          }
        },
        {
          "t": "ός",
          "ch": {
            "morph": "suf",
            "case": "n"
          }
        }
      ]
    },
    {
      "txt": "ἐσμεν",
      "lem": "εἰμί",
      "prs": "pres act ind 1 pl",
      "stm": "ἐσ",
      "ve": "μεν",
      "segs": [
        {
          "t": "ἐσ",
          "ch": {
            "morph": "stm"
          }
        },
        {
          "t": "μεν",
          "ch": {
            "morph": "ve"
          }
        }
      ],
      "tvm": "PAI",
      "igl": "is"
    },
    {
      "txt": "ἡμεῖς,",
      "lem": "ἐγώ",
      "prs": "pers.pron nom pl",
      "stm": "ἡμ",
      "suf": "εῖς",
      "cs": "n",
      "segs": [
        {
          "t": "ἡμ",
          "ch": {
            "morph": "stm"
          }
        },
        {
          "t": "εῖς",
          "ch": {
            "morph": "suf",
            "case": "n"
          }
        }
      ]
    },
    {
      "br": true
    },
    {
      "txt": "ἐὰν",
      "lem": "ἐάν",
      "prs": "conj"
    },
    {
      "txt": "τὴν",
      "lem": "ὁ",
      "prs": "art acc sg fem",
      "stm": "τὴν",
      "cs": "a",
      "segs": [
        {
          "t": "τὴν",
          "ch": {
            "morph": "suf",
            "case": "a"
          }
        }
      ]
    },
    {
      "txt": "παρρησίαν",
      "lem": "παρρησία",
      "prs": "noun acc sg fem",
      "stm": "παρρησί",
      "suf": "αν",
      "cs": "a",
      "segs": [
        {
          "t": "παρρησί",
          "ch": {
            "morph": "stm"
          }
        },
        {
          "t": "αν",
          "ch": {
            "morph": "suf",
            "case": "a"
          }
        }
      ]
    },
    {
      "txt": "καὶ",
      "lem": "καί",
      "prs": "conj"
    },
    {
      "txt": "τὸ",
      "lem": "ὁ",
      "prs": "art acc sg neut",
      "stm": "τὸ",
      "cs": "a",
      "segs": [
        {
          "t": "τὸ",
          "ch": {
            "morph": "suf",
            "case": "a"
          }
        }
      ]
    },
    {
      "txt": "καύχημα",
      "lem": "καύχημα",
      "prs": "noun acc sg neut",
      "stm": "καύχημ",
      "suf": "α",
      "cs": "a",
      "segs": [
        {
          "t": "καύχημ",
          "ch": {
            "morph": "stm"
          }
        },
        {
          "t": "α",
          "ch": {
            "morph": "suf",
            "case": "a"
          }
        }
      ]
    },
    {
      "txt": "τῆς",
      "lem": "ὁ",
      "prs": "art gen sg fem",
      "stm": "τῆς",
      "cs": "g",
      "segs": [
        {
          "t": "τῆς",
          "ch": {
            "morph": "suf",
            "case": "g"
          }
        }
      ]
    },
    {
      "txt": "ἐλπίδος",
      "lem": "ἐλπίς",
      "prs": "noun gen sg fem",
      "stm": "ἐλπίδ",
      "suf": "ος",
      "cs": "g",
      "segs": [
        {
          "t": "ἐλπίδ",
          "ch": {
            "morph": "stm"
          }
        },
        {
          "t": "ος",
          "ch": {
            "morph": "suf",
            "case": "g"
          }
        }
      ]
    },
    {
      "txt": "κατάσχωμεν.",
      "lem": "κατέχω",
      "prs": "aor act subj 1 pl",
      "pfx": "κατά",
      "stm": "σχ",
      "ve": "ωμεν",
      "segs": [
        {
          "t": "κατά",
          "ch": {
            "morph": "pfx"
          }
        },
        {
          "t": "σχ",
          "ch": {
            "morph": "stm"
          }
        },
        {
          "t": "ωμεν",
          "ch": {
            "morph": "ve"
          }
        }
      ],
      "tvm": "AAS"
    },
    {
      "br": true
    },
    {
      "v": 7
    },
    {
      "txt": "Διό,",
      "lem": "διό",
      "prs": "conj"
    },
    {
      "txt": "καθὼς",
      "lem": "καθώς",
      "prs": "conj"
    },
    {
      "txt": "λέγει",
      "lem": "λέγω",
      "prs": "pres act ind 3 sg",
      "stm": "λέγ",
      "ve": "ει",
      "segs": [
        {
          "t": "λέγ",
          "ch": {
            "morph": "stm"
          }
        },
        {
          "t": "ει",
          "ch": {
            "morph": "ve"
          }
        }
      ],
      "tvm": "PAI"
    },
    {
      "txt": "τὸ",
      "lem": "ὁ",
      "prs": "art nom sg neut",
      "stm": "τὸ",
      "cs": "n",
      "segs": [
        {
          "t": "τὸ",
          "ch": {
            "morph": "suf",
            "case": "n"
          }
        }
      ]
    },
    {
      "txt": "πνεῦμα",
      "lem": "πνεῦμα",
      "prs": "noun nom sg neut",
      "stm": "πνεῦμ",
      "suf": "α",
      "cs": "n",
      "segs": [
        {
          "t": "πνεῦμ",
          "ch": {
            "morph": "stm"
          }
        },
        {
          "t": "α",
          "ch": {
            "morph": "suf",
            "case": "n"
          }
        }
      ]
    },
    {
      "txt": "τὸ",
      "lem": "ὁ",
      "prs": "art nom sg neut",
      "stm": "τὸ",
      "cs": "n",
      "segs": [
        {
          "t": "τὸ",
          "ch": {
            "morph": "suf",
            "case": "n"
          }
        }
      ]
    },
    {
      "txt": "ἅγιον·",
      "lem": "ἅγιος",
      "prs": "adj nom sg neut",
      "stm": "ἅγι",
      "suf": "ον",
      "cs": "n",
      "segs": [
        {
          "t": "ἅγι",
          "ch": {
            "morph": "stm"
          }
        },
        {
          "t": "ον",
          "ch": {
            "morph": "suf",
            "case": "n"
          }
        }
      ]
    },
    {
      "br": true
    },
    {
      "txt": "Σήμερον",
      "lem": "σήμερον",
      "prs": "adv"
    },
    {
      "txt": "ἐὰν",
      "lem": "ἐάν",
      "prs": "conj"
    },
    {
      "txt": "τῆς",
      "lem": "ὁ",
      "prs": "art gen sg fem",
      "stm": "τῆς",
      "cs": "g",
      "segs": [
        {
          "t": "τῆς",
          "ch": {
            "morph": "suf",
            "case": "g"
          }
        }
      ]
    },
    {
      "txt": "φωνῆς",
      "lem": "φωνή",
      "prs": "noun gen sg fem",
      "stm": "φων",
      "suf": "ῆς",
      "cs": "g",
      "segs": [
        {
          "t": "φων",
          "ch": {
            "morph": "stm"
          }
        },
        {
          "t": "ῆς",
          "ch": {
            "morph": "suf",
            "case": "g"
          }
        }
      ]
    },
    {
      "txt": "αὐτοῦ",
      "lem": "αὐτός",
      "prs": "pers.pron gen sg masc",
      "stm": "αὐτ",
      "suf": "οῦ",
      "cs": "g",
      "segs": [
        {
          "t": "αὐτ",
          "ch": {
            "morph": "stm"
          }
        },
        {
          "t": "οῦ",
          "ch": {
            "morph": "suf",
            "case": "g"
          }
        }
      ]
    },
    {
      "txt": "ἀκούσητε,",
      "lem": "ἀκούω",
      "prs": "aor act subj 2 pl",
      "stm": "ἀκού",
      "frm": "ση",
      "ve": "τε",
      "segs": [
        {
          "t": "ἀκού",
          "ch": {
            "morph": "stm"
          }
        },
        {
          "t": "ση",
          "ch": {
            "morph": "frm"
          }
        },
        {
          "t": "τε",
          "ch": {
            "morph": "ve"
          }
        }
      ],
      "tvm": "AAS"
    },
    {
      "br": true
    },
    {
      "v": 8
    },
    {
      "txt": "μὴ",
      "lem": "μή",
      "prs": "adv"
    },
    {
      "txt": "σκληρύνητε",
      "lem": "σκληρύνω",
      "prs": "aor act subj 2 pl",
      "stm": "σκληρύν",
      "ve": "ητε",
      "segs": [
        {
          "t": "σκληρύν",
          "ch": {
            "morph": "stm"
          }
        },
        {
          "t": "ητε",
          "ch": {
            "morph": "ve"
          }
        }
      ],
      "tvm": "AAS"
    },
    {
      "txt": "τὰς",
      "lem": "ὁ",
      "prs": "art acc pl fem",
      "stm": "τὰς",
      "cs": "a",
      "segs": [
        {
          "t": "τὰς",
          "ch": {
            "morph": "suf",
            "case": "a"
          }
        }
      ]
    },
    {
      "txt": "καρδίας",
      "lem": "καρδία",
      "prs": "noun acc pl fem",
      "stm": "καρδί",
      "suf": "ας",
      "cs": "a",
      "segs": [
        {
          "t": "καρδί",
          "ch": {
            "morph": "stm"
          }
        },
        {
          "t": "ας",
          "ch": {
            "morph": "suf",
            "case": "a"
          }
        }
      ]
    },
    {
      "txt": "ὑμῶν",
      "lem": "σύ",
      "prs": "pers.pron gen pl",
      "stm": "ὑμ",
      "suf": "ῶν",
      "cs": "g",
      "segs": [
        {
          "t": "ὑμ",
          "ch": {
            "morph": "stm"
          }
        },
        {
          "t": "ῶν",
          "ch": {
            "morph": "suf",
            "case": "g"
          }
        }
      ]
    },
    {
      "txt": "ὡς",
      "lem": "ὡς",
      "prs": "conj"
    },
    {
      "txt": "ἐν",
      "lem": "ἐν",
      "prs": "prep"
    },
    {
      "txt": "τῷ",
      "lem": "ὁ",
      "prs": "art dat sg masc",
      "stm": "τῷ",
      "cs": "d",
      "segs": [
        {
          "t": "τῷ",
          "ch": {
            "morph": "suf",
            "case": "d"
          }
        }
      ]
    },
    {
      "txt": "παραπικρασμῷ,",
      "lem": "παραπικρασμός",
      "prs": "noun dat sg masc",
      "stm": "παραπικρασμ",
      "suf": "ῷ",
      "cs": "d",
      "segs": [
        {
          "t": "παραπικρασμ",
          "ch": {
            "morph": "stm"
          }
        },
        {
          "t": "ῷ",
          "ch": {
            "morph": "suf",
            "case": "d"
          }
        }
      ]
    },
    {
      "txt": "κατὰ",
      "lem": "κατά",
      "prs": "prep"
    },
    {
      "txt": "τὴν",
      "lem": "ὁ",
      "prs": "art acc sg fem",
      "stm": "τὴν",
      "cs": "a",
      "segs": [
        {
          "t": "τὴν",
          "ch": {
            "morph": "suf",
            "case": "a"
          }
        }
      ]
    },
    {
      "txt": "ἡμέραν",
      "lem": "ἡμέρα",
      "prs": "noun acc sg fem",
      "stm": "ἡμέρ",
      "suf": "αν",
      "cs": "a",
      "segs": [
        {
          "t": "ἡμέρ",
          "ch": {
            "morph": "stm"
          }
        },
        {
          "t": "αν",
          "ch": {
            "morph": "suf",
            "case": "a"
          }
        }
      ]
    },
    {
      "txt": "τοῦ",
      "lem": "ὁ",
      "prs": "art gen sg masc",
      "stm": "τοῦ",
      "cs": "g",
      "segs": [
        {
          "t": "τοῦ",
          "ch": {
            "morph": "suf",
            "case": "g"
          }
        }
      ]
    },
    {
      "txt": "πειρασμοῦ",
      "lem": "πειρασμός",
      "prs": "noun gen sg masc",
      "stm": "πειρασμ",
      "suf": "οῦ",
      "cs": "g",
      "segs": [
        {
          "t": "πειρασμ",
          "ch": {
            "morph": "stm"
          }
        },
        {
          "t": "οῦ",
          "ch": {
            "morph": "suf",
            "case": "g"
          }
        }
      ]
    },
    {
      "txt": "ἐν",
      "lem": "ἐν",
      "prs": "prep"
    },
    {
      "txt": "τῇ",
      "lem": "ὁ",
      "prs": "art dat sg fem",
      "stm": "τῇ",
      "cs": "d",
      "segs": [
        {
          "t": "τῇ",
          "ch": {
            "morph": "suf",
            "case": "d"
          }
        }
      ]
    },
    {
      "txt": "ἐρήμῳ,",
      "lem": "ἔρημος",
      "prs": "adj dat sg fem",
      "stm": "ἐρήμ",
      "suf": "ῳ",
      "cs": "d",
      "segs": [
        {
          "t": "ἐρήμ",
          "ch": {
            "morph": "stm"
          }
        },
        {
          "t": "ῳ",
          "ch": {
            "morph": "suf",
            "case": "d"
          }
        }
      ]
    },
    {
      "br": true
    },
    {
      "v": 9
    },
    {
      "txt": "οὗ",
      "lem": "οὗ",
      "prs": "adv"
    },
    {
      "txt": "ἐπείρασαν",
      "lem": "πειράζω",
      "prs": "aor act ind 3 pl",
      "aug": "ἐ",
      "stm": "πείρα",
      "frm": "σα",
      "ve": "ν",
      "segs": [
        {
          "t": "ἐ",
          "ch": {
            "morph": "aug"
          }
        },
        {
          "t": "πείρα",
          "ch": {
            "morph": "stm"
          }
        },
        {
          "t": "σα",
          "ch": {
            "morph": "frm"
          }
        },
        {
          "t": "ν",
          "ch": {
            "morph": "ve"
          }
        }
      ],
      "tvm": "AAI",
      "igl": "tried"
    },
    {
      "txt": "οἱ",
      "lem": "ὁ",
      "prs": "art nom pl masc",
      "stm": "οἱ",
      "cs": "n",
      "segs": [
        {
          "t": "οἱ",
          "ch": {
            "morph": "suf",
            "case": "n"
          }
        }
      ]
    },
    {
      "txt": "πατέρες",
      "lem": "πατήρ",
      "prs": "noun nom pl masc",
      "stm": "πατέρ",
      "suf": "ες",
      "cs": "n",
      "segs": [
        {
          "t": "πατέρ",
          "ch": {
            "morph": "stm"
          }
        },
        {
          "t": "ες",
          "ch": {
            "morph": "suf",
            "case": "n"
          }
        }
      ]
    },
    {
      "txt": "ὑμῶν",
      "lem": "σύ",
      "prs": "pers.pron gen pl",
      "stm": "ὑμ",
      "suf": "ῶν",
      "cs": "g",
      "segs": [
        {
          "t": "ὑμ",
          "ch": {
            "morph": "stm"
          }
        },
        {
          "t": "ῶν",
          "ch": {
            "morph": "suf",
            "case": "g"
          }
        }
      ]
    },
    {
      "txt": "ἐν",
      "lem": "ἐν",
      "prs": "prep"
    },
    {
      "txt": "δοκιμασίᾳ",
      "lem": "δοκιμασία",
      "prs": "noun dat sg fem",
      "stm": "δοκιμασί",
      "suf": "ᾳ",
      "cs": "d",
      "segs": [
        {
          "t": "δοκιμασί",
          "ch": {
            "morph": "stm"
          }
        },
        {
          "t": "ᾳ",
          "ch": {
            "morph": "suf",
            "case": "d"
          }
        }
      ]
    },
    {
      "br": true
    },
    {
      "txt": "καὶ",
      "lem": "καί",
      "prs": "conj"
    },
    {
      "txt": "εἶδον",
      "lem": "ὁράω",
      "prs": "aor act ind 3 pl",
      "aug": "ε",
      "stm": "ἶδ",
      "ve": "ον",
      "segs": [
        {
          "t": "ε",
          "ch": {
            "morph": "aug"
          }
        },
        {
          "t": "ἶδ",
          "ch": {
            "morph": "stm"
          }
        },
        {
          "t": "ον",
          "ch": {
            "morph": "ve"
          }
        }
      ],
      "tvm": "AAI",
      "igl": "saw"
    },
    {
      "txt": "τὰ",
      "lem": "ὁ",
      "prs": "art acc pl neut",
      "stm": "τὰ",
      "cs": "a",
      "segs": [
        {
          "t": "τὰ",
          "ch": {
            "morph": "suf",
            "case": "a"
          }
        }
      ]
    },
    {
      "txt": "ἔργα",
      "lem": "ἔργον",
      "prs": "noun acc pl neut",
      "stm": "ἔργ",
      "suf": "α",
      "cs": "a",
      "segs": [
        {
          "t": "ἔργ",
          "ch": {
            "morph": "stm"
          }
        },
        {
          "t": "α",
          "ch": {
            "morph": "suf",
            "case": "a"
          }
        }
      ]
    },
    {
      "txt": "μου",
      "lem": "ἐγώ",
      "prs": "pers.pron gen sg",
      "stm": "μ",
      "suf": "ου",
      "cs": "g",
      "segs": [
        {
          "t": "μ",
          "ch": {
            "morph": "stm"
          }
        },
        {
          "t": "ου",
          "ch": {
            "morph": "suf",
            "case": "g"
          }
        }
      ]
    },
    {
      "br": true
    },
    {
      "v": 10
    },
    {
      "txt": "τεσσεράκοντα",
      "lem": "τεσσεράκοντα",
      "prs": "adj acc pl neut",
      "stm": "τεσσεράκοντ",
      "suf": "α",
      "cs": "a",
      "segs": [
        {
          "t": "τεσσεράκοντ",
          "ch": {
            "morph": "stm"
          }
        },
        {
          "t": "α",
          "ch": {
            "morph": "suf",
            "case": "a"
          }
        }
      ]
    },
    {
      "txt": "ἔτη·",
      "lem": "ἔτος",
      "prs": "noun acc pl neut",
      "stm": "ἔτ",
      "suf": "η",
      "cs": "a",
      "segs": [
        {
          "t": "ἔτ",
          "ch": {
            "morph": "stm"
          }
        },
        {
          "t": "η",
          "ch": {
            "morph": "suf",
            "case": "a"
          }
        }
      ]
    },
    {
      "br": true
    },
    {
      "txt": "διὸ",
      "lem": "διό",
      "prs": "conj"
    },
    {
      "txt": "προσώχθισα",
      "lem": "προσοχθίζω",
      "prs": "aor act ind 1 sg",
      "pfx": "προσ",
      "aug": "ώ",
      "stm": "χθι",
      "frm": "σα",
      "segs": [
        {
          "t": "προσ",
          "ch": {
            "morph": "pfx"
          }
        },
        {
          "t": "ώ",
          "ch": {
            "morph": "aug"
          }
        },
        {
          "t": "χθι",
          "ch": {
            "morph": "stm"
          }
        },
        {
          "t": "σα",
          "ch": {
            "morph": "frm"
          }
        }
      ],
      "tvm": "AAI",
      "igl": "was displeased with"
    },
    {
      "txt": "τῇ",
      "lem": "ὁ",
      "prs": "art dat sg fem",
      "stm": "τῇ",
      "cs": "d",
      "segs": [
        {
          "t": "τῇ",
          "ch": {
            "morph": "suf",
            "case": "d"
          }
        }
      ]
    },
    {
      "txt": "γενεᾷ",
      "lem": "γενεά",
      "prs": "noun dat sg fem",
      "stm": "γενε",
      "suf": "ᾷ",
      "cs": "d",
      "segs": [
        {
          "t": "γενε",
          "ch": {
            "morph": "stm"
          }
        },
        {
          "t": "ᾷ",
          "ch": {
            "morph": "suf",
            "case": "d"
          }
        }
      ]
    },
    {
      "txt": "ταύτῃ",
      "lem": "οὗτος",
      "prs": "dem.pron dat sg fem",
      "stm": "ταύτ",
      "suf": "ῃ",
      "cs": "d",
      "segs": [
        {
          "t": "ταύτ",
          "ch": {
            "morph": "stm"
          }
        },
        {
          "t": "ῃ",
          "ch": {
            "morph": "suf",
            "case": "d"
          }
        }
      ]
    },
    {
      "br": true
    },
    {
      "txt": "καὶ",
      "lem": "καί",
      "prs": "conj"
    },
    {
      "txt": "εἶπον·",
      "lem": "λέγω",
      "prs": "aor act ind 1 sg",
      "aug": "εἶ",
      "stm": "π",
      "ve": "ον",
      "segs": [
        {
          "t": "εἶ",
          "ch": {
            "morph": "aug"
          }
        },
        {
          "t": "π",
          "ch": {
            "morph": "stm"
          }
        },
        {
          "t": "ον",
          "ch": {
            "morph": "ve"
          }
        }
      ],
      "tvm": "AAI",
      "igl": "said"
    },
    {
      "txt": "Ἀεὶ",
      "lem": "ἀεί",
      "prs": "adv"
    },
    {
      "txt": "πλανῶνται",
      "lem": "πλανάω",
      "prs": "pres pass ind 3 pl",
      "stm": "πλανῶνται",
      "segs": [
        {
          "t": "πλανῶνται",
          "ch": {
            "morph": "stm"
          }
        }
      ],
      "tvm": "PPI",
      "igl": "is led astray"
    },
    {
      "txt": "τῇ",
      "lem": "ὁ",
      "prs": "art dat sg fem",
      "stm": "τῇ",
      "cs": "d",
      "segs": [
        {
          "t": "τῇ",
          "ch": {
            "morph": "suf",
            "case": "d"
          }
        }
      ]
    },
    {
      "txt": "καρδίᾳ·",
      "lem": "καρδία",
      "prs": "noun dat sg fem",
      "stm": "καρδί",
      "suf": "ᾳ",
      "cs": "d",
      "segs": [
        {
          "t": "καρδί",
          "ch": {
            "morph": "stm"
          }
        },
        {
          "t": "ᾳ",
          "ch": {
            "morph": "suf",
            "case": "d"
          }
        }
      ]
    },
    {
      "br": true
    },
    {
      "txt": "αὐτοὶ",
      "lem": "αὐτός",
      "prs": "pers.pron nom pl masc",
      "stm": "αὐτ",
      "suf": "οὶ",
      "cs": "n",
      "segs": [
        {
          "t": "αὐτ",
          "ch": {
            "morph": "stm"
          }
        },
        {
          "t": "οὶ",
          "ch": {
            "morph": "suf",
            "case": "n"
          }
        }
      ]
    },
    {
      "txt": "δὲ",
      "lem": "δέ",
      "prs": "conj"
    },
    {
      "txt": "οὐκ",
      "lem": "οὐ",
      "prs": "adv"
    },
    {
      "txt": "ἔγνωσαν",
      "lem": "γινώσκω",
      "prs": "aor act ind 3 pl",
      "aug": "ἔ",
      "stm": "γνω",
      "ve": "σαν",
      "segs": [
        {
          "t": "ἔ",
          "ch": {
            "morph": "aug"
          }
        },
        {
          "t": "γνω",
          "ch": {
            "morph": "stm"
          }
        },
        {
          "t": "σαν",
          "ch": {
            "morph": "ve"
          }
        }
      ],
      "tvm": "AAI",
      "igl": "came to know"
    },
    {
      "txt": "τὰς",
      "lem": "ὁ",
      "prs": "art acc pl fem",
      "stm": "τὰς",
      "cs": "a",
      "segs": [
        {
          "t": "τὰς",
          "ch": {
            "morph": "suf",
            "case": "a"
          }
        }
      ]
    },
    {
      "txt": "ὁδούς",
      "lem": "ὁδός",
      "prs": "noun acc pl fem",
      "stm": "ὁδ",
      "suf": "ούς",
      "cs": "a",
      "segs": [
        {
          "t": "ὁδ",
          "ch": {
            "morph": "stm"
          }
        },
        {
          "t": "ούς",
          "ch": {
            "morph": "suf",
            "case": "a"
          }
        }
      ]
    },
    {
      "txt": "μου·",
      "lem": "ἐγώ",
      "prs": "pers.pron gen sg",
      "stm": "μ",
      "suf": "ου",
      "cs": "g",
      "segs": [
        {
          "t": "μ",
          "ch": {
            "morph": "stm"
          }
        },
        {
          "t": "ου",
          "ch": {
            "morph": "suf",
            "case": "g"
          }
        }
      ]
    },
    {
      "br": true
    },
    {
      "v": 11
    },
    {
      "txt": "ὡς",
      "lem": "ὡς",
      "prs": "conj"
    },
    {
      "txt": "ὤμοσα",
      "lem": "ὀμνύω",
      "prs": "aor act ind 1 sg",
      "aug": "ὤ",
      "stm": "μο",
      "frm": "σα",
      "segs": [
        {
          "t": "ὤ",
          "ch": {
            "morph": "aug"
          }
        },
        {
          "t": "μο",
          "ch": {
            "morph": "stm"
          }
        },
        {
          "t": "σα",
          "ch": {
            "morph": "frm"
          }
        }
      ],
      "tvm": "AAI",
      "igl": "sweared"
    },
    {
      "txt": "ἐν",
      "lem": "ἐν",
      "prs": "prep"
    },
    {
      "txt": "τῇ",
      "lem": "ὁ",
      "prs": "art dat sg fem",
      "stm": "τῇ",
      "cs": "d",
      "segs": [
        {
          "t": "τῇ",
          "ch": {
            "morph": "suf",
            "case": "d"
          }
        }
      ]
    },
    {
      "txt": "ὀργῇ",
      "lem": "ὀργή",
      "prs": "noun dat sg fem",
      "stm": "ὀργ",
      "suf": "ῇ",
      "cs": "d",
      "segs": [
        {
          "t": "ὀργ",
          "ch": {
            "morph": "stm"
          }
        },
        {
          "t": "ῇ",
          "ch": {
            "morph": "suf",
            "case": "d"
          }
        }
      ]
    },
    {
      "txt": "μου·",
      "lem": "ἐγώ",
      "prs": "pers.pron gen sg",
      "stm": "μ",
      "suf": "ου",
      "cs": "g",
      "segs": [
        {
          "t": "μ",
          "ch": {
            "morph": "stm"
          }
        },
        {
          "t": "ου",
          "ch": {
            "morph": "suf",
            "case": "g"
          }
        }
      ]
    },
    {
      "br": true
    },
    {
      "txt": "Εἰ",
      "lem": "εἰ",
      "prs": "conj"
    },
    {
      "txt": "εἰσελεύσονται",
      "lem": "εἰσέρχομαι",
      "prs": "fut mid ind 3 pl",
      "pfx": "εἰσ",
      "stm": "ελεύ",
      "frm": "σο",
      "ve": "νται",
      "segs": [
        {
          "t": "εἰσ",
          "ch": {
            "morph": "pfx"
          }
        },
        {
          "t": "ελεύ",
          "ch": {
            "morph": "stm"
          }
        },
        {
          "t": "σο",
          "ch": {
            "morph": "frm"
          }
        },
        {
          "t": "νται",
          "ch": {
            "morph": "ve"
          }
        }
      ],
      "tvm": "FMI",
      "igl": "will go in"
    },
    {
      "txt": "εἰς",
      "lem": "εἰς",
      "prs": "prep"
    },
    {
      "txt": "τὴν",
      "lem": "ὁ",
      "prs": "art acc sg fem",
      "stm": "τὴν",
      "cs": "a",
      "segs": [
        {
          "t": "τὴν",
          "ch": {
            "morph": "suf",
            "case": "a"
          }
        }
      ]
    },
    {
      "txt": "κατάπαυσίν",
      "lem": "κατάπαυσις",
      "prs": "noun acc sg fem",
      "stm": "κατάπαυσ",
      "suf": "ίν",
      "cs": "a",
      "segs": [
        {
          "t": "κατάπαυσ",
          "ch": {
            "morph": "stm"
          }
        },
        {
          "t": "ίν",
          "ch": {
            "morph": "suf",
            "case": "a"
          }
        }
      ]
    },
    {
      "txt": "μου.",
      "lem": "ἐγώ",
      "prs": "pers.pron gen sg",
      "stm": "μ",
      "suf": "ου",
      "cs": "g",
      "segs": [
        {
          "t": "μ",
          "ch": {
            "morph": "stm"
          }
        },
        {
          "t": "ου",
          "ch": {
            "morph": "suf",
            "case": "g"
          }
        }
      ]
    },
    {
      "br": true
    },
    {
      "v": 12
    },
    {
      "txt": "βλέπετε,",
      "lem": "βλέπω",
      "prs": "pres act imp 2 pl",
      "stm": "βλέπ",
      "ve": "ετε",
      "segs": [
        {
          "t": "βλέπ",
          "ch": {
            "morph": "stm"
          }
        },
        {
          "t": "ετε",
          "ch": {
            "morph": "ve"
          }
        }
      ],
      "tvm": "PAD"
    },
    {
      "txt": "ἀδελφοί,",
      "lem": "ἀδελφός",
      "prs": "noun voc pl masc",
      "stm": "ἀδελφ",
      "suf": "οί",
      "cs": "v",
      "segs": [
        {
          "t": "ἀδελφ",
          "ch": {
            "morph": "stm"
          }
        },
        {
          "t": "οί",
          "ch": {
            "morph": "suf",
            "case": "v"
          }
        }
      ]
    },
    {
      "br": true
    },
    {
      "txt": "μήποτε",
      "lem": "μήποτε",
      "prs": "conj"
    },
    {
      "txt": "ἔσται",
      "lem": "εἰμί",
      "prs": "fut mid ind 3 sg",
      "stm": "ἔσ",
      "ve": "ται",
      "segs": [
        {
          "t": "ἔσ",
          "ch": {
            "morph": "stm"
          }
        },
        {
          "t": "ται",
          "ch": {
            "morph": "ve"
          }
        }
      ],
      "tvm": "FMI",
      "igl": "will be"
    },
    {
      "txt": "ἔν",
      "lem": "ἐν",
      "prs": "prep"
    },
    {
      "txt": "τινι",
      "lem": "τις",
      "prs": "inter.pron dat sg masc",
      "stm": "τιν",
      "suf": "ι",
      "cs": "d",
      "segs": [
        {
          "t": "τιν",
          "ch": {
            "morph": "stm"
          }
        },
        {
          "t": "ι",
          "ch": {
            "morph": "suf",
            "case": "d"
          }
        }
      ]
    },
    {
      "txt": "ὑμῶν",
      "lem": "σύ",
      "prs": "pers.pron gen pl",
      "stm": "ὑμ",
      "suf": "ῶν",
      "cs": "g",
      "segs": [
        {
          "t": "ὑμ",
          "ch": {
            "morph": "stm"
          }
        },
        {
          "t": "ῶν",
          "ch": {
            "morph": "suf",
            "case": "g"
          }
        }
      ]
    },
    {
      "txt": "καρδία",
      "lem": "καρδία",
      "prs": "noun nom sg fem",
      "stm": "καρδί",
      "suf": "α",
      "cs": "n",
      "segs": [
        {
          "t": "καρδί",
          "ch": {
            "morph": "stm"
          }
        },
        {
          "t": "α",
          "ch": {
            "morph": "suf",
            "case": "n"
          }
        }
      ]
    },
    {
      "txt": "πονηρὰ",
      "lem": "πονηρός",
      "prs": "adj nom sg fem",
      "stm": "πονηρ",
      "suf": "ὰ",
      "cs": "n",
      "segs": [
        {
          "t": "πονηρ",
          "ch": {
            "morph": "stm"
          }
        },
        {
          "t": "ὰ",
          "ch": {
            "morph": "suf",
            "case": "n"
          }
        }
      ]
    },
    {
      "txt": "ἀπιστίας",
      "lem": "ἀπιστία",
      "prs": "noun gen sg fem",
      "stm": "ἀπιστί",
      "suf": "ας",
      "cs": "g",
      "segs": [
        {
          "t": "ἀπιστί",
          "ch": {
            "morph": "stm"
          }
        },
        {
          "t": "ας",
          "ch": {
            "morph": "suf",
            "case": "g"
          }
        }
      ]
    },
    {
      "br": true
    },
    {
      "txt": "ἐν",
      "lem": "ἐν",
      "prs": "prep"
    },
    {
      "txt": "τῷ",
      "lem": "ὁ",
      "prs": "art dat sg neut",
      "stm": "τῷ",
      "cs": "d",
      "segs": [
        {
          "t": "τῷ",
          "ch": {
            "morph": "suf",
            "case": "d"
          }
        }
      ]
    },
    {
      "txt": "ἀποστῆναι",
      "lem": "ἀφίσταμαι",
      "prs": "aor act inf",
      "pfx": "ἀπο",
      "stm": "στῆ",
      "ve": "ναι",
      "segs": [
        {
          "t": "ἀπο",
          "ch": {
            "morph": "pfx"
          }
        },
        {
          "t": "στῆ",
          "ch": {
            "morph": "stm"
          }
        },
        {
          "t": "ναι",
          "ch": {
            "morph": "ve"
          }
        }
      ],
      "tvm": "AAN"
    },
    {
      "txt": "ἀπὸ",
      "lem": "ἀπό",
      "prs": "prep"
    },
    {
      "txt": "θεοῦ",
      "lem": "θεός",
      "prs": "noun gen sg masc",
      "stm": "θε",
      "suf": "οῦ",
      "cs": "g",
      "segs": [
        {
          "t": "θε",
          "ch": {
            "morph": "stm"
          }
        },
        {
          "t": "οῦ",
          "ch": {
            "morph": "suf",
            "case": "g"
          }
        }
      ]
    },
    {
      "txt": "ζῶντος,",
      "lem": "ζάω",
      "prs": "pres act ptc gen sg masc",
      "stm": "ζ",
      "ptc": "ῶντ",
      "suf": "ος",
      "cs": "g",
      "segs": [
        {
          "t": "ζ",
          "ch": {
            "morph": "stm"
          }
        },
        {
          "t": "ῶντ",
          "ch": {
            "morph": "pmk",
            "ptc": "marker"
          }
        },
        {
          "t": "ος",
          "ch": {
            "morph": "suf",
            "ptc": "marker",
            "case": "g"
          }
        }
      ],
      "tvm": "PAP"
    },
    {
      "br": true
    },
    {
      "v": 13
    },
    {
      "txt": "ἀλλὰ",
      "lem": "ἀλλά",
      "prs": "conj"
    },
    {
      "txt": "παρακαλεῖτε",
      "lem": "παρακαλέω",
      "prs": "pres act imp 2 pl",
      "pfx": "παρα",
      "stm": "καλε",
      "ve": "ῖτε",
      "segs": [
        {
          "t": "παρα",
          "ch": {
            "morph": "pfx"
          }
        },
        {
          "t": "καλε",
          "ch": {
            "morph": "stm"
          }
        },
        {
          "t": "ῖτε",
          "ch": {
            "morph": "ve"
          }
        }
      ],
      "tvm": "PAD"
    },
    {
      "txt": "ἑαυτοὺς",
      "lem": "ἑαυτοῦ",
      "prs": "pers.pron acc pl masc",
      "stm": "ἑαυτ",
      "suf": "οὺς",
      "cs": "a",
      "segs": [
        {
          "t": "ἑαυτ",
          "ch": {
            "morph": "stm"
          }
        },
        {
          "t": "οὺς",
          "ch": {
            "morph": "suf",
            "case": "a"
          }
        }
      ]
    },
    {
      "txt": "καθʼ",
      "lem": "κατά",
      "prs": "prep"
    },
    {
      "txt": "ἑκάστην",
      "lem": "ἕκαστος",
      "prs": "adj acc sg fem",
      "stm": "ἑκάστ",
      "suf": "ην",
      "cs": "a",
      "segs": [
        {
          "t": "ἑκάστ",
          "ch": {
            "morph": "stm"
          }
        },
        {
          "t": "ην",
          "ch": {
            "morph": "suf",
            "case": "a"
          }
        }
      ]
    },
    {
      "txt": "ἡμέραν,",
      "lem": "ἡμέρα",
      "prs": "noun acc sg fem",
      "stm": "ἡμέρ",
      "suf": "αν",
      "cs": "a",
      "segs": [
        {
          "t": "ἡμέρ",
          "ch": {
            "morph": "stm"
          }
        },
        {
          "t": "αν",
          "ch": {
            "morph": "suf",
            "case": "a"
          }
        }
      ]
    },
    {
      "br": true
    },
    {
      "txt": "ἄχρις",
      "lem": "ἄχρις",
      "prs": "prep"
    },
    {
      "txt": "οὗ",
      "lem": "ὅς",
      "prs": "rel.pron gen sg masc",
      "stm": "οὗ",
      "segs": [
        {
          "t": "οὗ",
          "ch": {
            "morph": "stm"
          }
        }
      ]
    },
    {
      "txt": "τὸ",
      "lem": "ὁ",
      "prs": "art nom sg neut",
      "stm": "τὸ",
      "cs": "n",
      "segs": [
        {
          "t": "τὸ",
          "ch": {
            "morph": "suf",
            "case": "n"
          }
        }
      ]
    },
    {
      "txt": "Σήμερον",
      "lem": "σήμερον",
      "prs": "adv"
    },
    {
      "txt": "καλεῖται,",
      "lem": "καλέω",
      "prs": "pres pass ind 3 sg",
      "stm": "καλε",
      "ve": "ῖται",
      "segs": [
        {
          "t": "καλε",
          "ch": {
            "morph": "stm"
          }
        },
        {
          "t": "ῖται",
          "ch": {
            "morph": "ve"
          }
        }
      ],
      "tvm": "PPI",
      "igl": "is called"
    },
    {
      "br": true
    },
    {
      "txt": "ἵνα",
      "lem": "ἵνα",
      "prs": "conj"
    },
    {
      "txt": "μὴ",
      "lem": "μή",
      "prs": "adv"
    },
    {
      "txt": "σκληρυνθῇ",
      "lem": "σκληρύνω",
      "prs": "aor pass subj 3 sg",
      "stm": "σκληρυν",
      "frm": "θῇ",
      "segs": [
        {
          "t": "σκληρυν",
          "ch": {
            "morph": "stm"
          }
        },
        {
          "t": "θῇ",
          "ch": {
            "morph": "frm"
          }
        }
      ],
      "tvm": "APS",
      "igl": "be hardened"
    },
    {
      "txt": "τις",
      "lem": "τις",
      "prs": "inter.pron nom sg masc",
      "stm": "τ",
      "suf": "ις",
      "cs": "n",
      "segs": [
        {
          "t": "τ",
          "ch": {
            "morph": "stm"
          }
        },
        {
          "t": "ις",
          "ch": {
            "morph": "suf",
            "case": "n"
          }
        }
      ]
    },
    {
      "txt": "ἐξ",
      "lem": "ἐκ",
      "prs": "prep"
    },
    {
      "txt": "ὑμῶν",
      "lem": "σύ",
      "prs": "pers.pron gen pl",
      "stm": "ὑμ",
      "suf": "ῶν",
      "cs": "g",
      "segs": [
        {
          "t": "ὑμ",
          "ch": {
            "morph": "stm"
          }
        },
        {
          "t": "ῶν",
          "ch": {
            "morph": "suf",
            "case": "g"
          }
        }
      ]
    },
    {
      "txt": "ἀπάτῃ",
      "lem": "ἀπάτη",
      "prs": "noun dat sg fem",
      "stm": "ἀπάτ",
      "suf": "ῃ",
      "cs": "d",
      "segs": [
        {
          "t": "ἀπάτ",
          "ch": {
            "morph": "stm"
          }
        },
        {
          "t": "ῃ",
          "ch": {
            "morph": "suf",
            "case": "d"
          }
        }
      ]
    },
    {
      "txt": "τῆς",
      "lem": "ὁ",
      "prs": "art gen sg fem",
      "stm": "τῆς",
      "cs": "g",
      "segs": [
        {
          "t": "τῆς",
          "ch": {
            "morph": "suf",
            "case": "g"
          }
        }
      ]
    },
    {
      "txt": "ἁμαρτίας·",
      "lem": "ἁμαρτία",
      "prs": "noun gen sg fem",
      "stm": "ἁμαρτί",
      "suf": "ας",
      "cs": "g",
      "segs": [
        {
          "t": "ἁμαρτί",
          "ch": {
            "morph": "stm"
          }
        },
        {
          "t": "ας",
          "ch": {
            "morph": "suf",
            "case": "g"
          }
        }
      ]
    },
    {
      "br": true
    },
    {
      "v": 14
    },
    {
      "txt": "μέτοχοι",
      "lem": "μέτοχος",
      "prs": "adj nom pl masc",
      "stm": "μέτοχ",
      "suf": "οι",
      "cs": "n",
      "segs": [
        {
          "t": "μέτοχ",
          "ch": {
            "morph": "stm"
          }
        },
        {
          "t": "οι",
          "ch": {
            "morph": "suf",
            "case": "n"
          }
        }
      ]
    },
    {
      "txt": "γὰρ",
      "lem": "γάρ",
      "prs": "conj"
    },
    {
      "txt": "τοῦ",
      "lem": "ὁ",
      "prs": "art gen sg masc",
      "stm": "τοῦ",
      "cs": "g",
      "segs": [
        {
          "t": "τοῦ",
          "ch": {
            "morph": "suf",
            "case": "g"
          }
        }
      ]
    },
    {
      "txt": "Χριστοῦ",
      "lem": "Χριστός",
      "prs": "noun gen sg masc",
      "stm": "Χριστ",
      "suf": "οῦ",
      "cs": "g",
      "segs": [
        {
          "t": "Χριστ",
          "ch": {
            "morph": "stm"
          }
        },
        {
          "t": "οῦ",
          "ch": {
            "morph": "suf",
            "case": "g"
          }
        }
      ]
    },
    {
      "txt": "γεγόναμεν",
      "lem": "γίνομαι",
      "prs": "perf act ind 1 pl",
      "rdp": "γε",
      "stm": "γόν",
      "ve": "αμεν",
      "segs": [
        {
          "t": "γε",
          "ch": {
            "morph": "rdp"
          }
        },
        {
          "t": "γόν",
          "ch": {
            "morph": "stm"
          }
        },
        {
          "t": "αμεν",
          "ch": {
            "morph": "ve"
          }
        }
      ],
      "tvm": "XAI"
    },
    {
      "br": true
    },
    {
      "txt": "ἐάνπερ",
      "lem": "ἐάνπερ",
      "prs": "conj"
    },
    {
      "txt": "τὴν",
      "lem": "ὁ",
      "prs": "art acc sg fem",
      "stm": "τὴν",
      "cs": "a",
      "segs": [
        {
          "t": "τὴν",
          "ch": {
            "morph": "suf",
            "case": "a"
          }
        }
      ]
    },
    {
      "txt": "ἀρχὴν",
      "lem": "ἀρχή",
      "prs": "noun acc sg fem",
      "stm": "ἀρχ",
      "suf": "ὴν",
      "cs": "a",
      "segs": [
        {
          "t": "ἀρχ",
          "ch": {
            "morph": "stm"
          }
        },
        {
          "t": "ὴν",
          "ch": {
            "morph": "suf",
            "case": "a"
          }
        }
      ]
    },
    {
      "txt": "τῆς",
      "lem": "ὁ",
      "prs": "art gen sg fem",
      "stm": "τῆς",
      "cs": "g",
      "segs": [
        {
          "t": "τῆς",
          "ch": {
            "morph": "suf",
            "case": "g"
          }
        }
      ]
    },
    {
      "txt": "ὑποστάσεως",
      "lem": "ὑπόστασις",
      "prs": "noun gen sg fem",
      "stm": "ὑποστάσ",
      "suf": "εως",
      "cs": "g",
      "segs": [
        {
          "t": "ὑποστάσ",
          "ch": {
            "morph": "stm"
          }
        },
        {
          "t": "εως",
          "ch": {
            "morph": "suf",
            "case": "g"
          }
        }
      ]
    },
    {
      "txt": "μέχρι",
      "lem": "μέχρι(ς)",
      "prs": "prep"
    },
    {
      "txt": "τέλους",
      "lem": "τέλος",
      "prs": "noun gen sg neut",
      "stm": "τέλ",
      "suf": "ους",
      "cs": "g",
      "segs": [
        {
          "t": "τέλ",
          "ch": {
            "morph": "stm"
          }
        },
        {
          "t": "ους",
          "ch": {
            "morph": "suf",
            "case": "g"
          }
        }
      ]
    },
    {
      "txt": "βεβαίαν",
      "lem": "βέβαιος",
      "prs": "adj acc sg fem",
      "stm": "βεβαί",
      "suf": "αν",
      "cs": "a",
      "segs": [
        {
          "t": "βεβαί",
          "ch": {
            "morph": "stm"
          }
        },
        {
          "t": "αν",
          "ch": {
            "morph": "suf",
            "case": "a"
          }
        }
      ]
    },
    {
      "txt": "κατάσχωμεν.",
      "lem": "κατέχω",
      "prs": "aor act subj 1 pl",
      "pfx": "κατά",
      "stm": "σχ",
      "ve": "ωμεν",
      "segs": [
        {
          "t": "κατά",
          "ch": {
            "morph": "pfx"
          }
        },
        {
          "t": "σχ",
          "ch": {
            "morph": "stm"
          }
        },
        {
          "t": "ωμεν",
          "ch": {
            "morph": "ve"
          }
        }
      ],
      "tvm": "AAS"
    },
    {
      "br": true
    },
    {
      "v": 15
    },
    {
      "txt": "ἐν",
      "lem": "ἐν",
      "prs": "prep"
    },
    {
      "txt": "τῷ",
      "lem": "ὁ",
      "prs": "art dat sg neut",
      "stm": "τῷ",
      "cs": "d",
      "segs": [
        {
          "t": "τῷ",
          "ch": {
            "morph": "suf",
            "case": "d"
          }
        }
      ]
    },
    {
      "txt": "λέγεσθαι·",
      "lem": "λέγω",
      "prs": "pres pass inf",
      "stm": "λέγ",
      "ve": "εσθαι",
      "segs": [
        {
          "t": "λέγ",
          "ch": {
            "morph": "stm"
          }
        },
        {
          "t": "εσθαι",
          "ch": {
            "morph": "ve"
          }
        }
      ],
      "tvm": "PPN",
      "igl": "to be said"
    },
    {
      "br": true
    },
    {
      "txt": "Σήμερον",
      "lem": "σήμερον",
      "prs": "adv"
    },
    {
      "txt": "ἐὰν",
      "lem": "ἐάν",
      "prs": "conj"
    },
    {
      "txt": "τῆς",
      "lem": "ὁ",
      "prs": "art gen sg fem",
      "stm": "τῆς",
      "cs": "g",
      "segs": [
        {
          "t": "τῆς",
          "ch": {
            "morph": "suf",
            "case": "g"
          }
        }
      ]
    },
    {
      "txt": "φωνῆς",
      "lem": "φωνή",
      "prs": "noun gen sg fem",
      "stm": "φων",
      "suf": "ῆς",
      "cs": "g",
      "segs": [
        {
          "t": "φων",
          "ch": {
            "morph": "stm"
          }
        },
        {
          "t": "ῆς",
          "ch": {
            "morph": "suf",
            "case": "g"
          }
        }
      ]
    },
    {
      "txt": "αὐτοῦ",
      "lem": "αὐτός",
      "prs": "pers.pron gen sg masc",
      "stm": "αὐτ",
      "suf": "οῦ",
      "cs": "g",
      "segs": [
        {
          "t": "αὐτ",
          "ch": {
            "morph": "stm"
          }
        },
        {
          "t": "οῦ",
          "ch": {
            "morph": "suf",
            "case": "g"
          }
        }
      ]
    },
    {
      "txt": "ἀκούσητε,",
      "lem": "ἀκούω",
      "prs": "aor act subj 2 pl",
      "stm": "ἀκού",
      "frm": "ση",
      "ve": "τε",
      "segs": [
        {
          "t": "ἀκού",
          "ch": {
            "morph": "stm"
          }
        },
        {
          "t": "ση",
          "ch": {
            "morph": "frm"
          }
        },
        {
          "t": "τε",
          "ch": {
            "morph": "ve"
          }
        }
      ],
      "tvm": "AAS"
    },
    {
      "br": true
    },
    {
      "txt": "Μὴ",
      "lem": "μή",
      "prs": "adv"
    },
    {
      "txt": "σκληρύνητε",
      "lem": "σκληρύνω",
      "prs": "aor act subj 2 pl",
      "stm": "σκληρύν",
      "ve": "ητε",
      "segs": [
        {
          "t": "σκληρύν",
          "ch": {
            "morph": "stm"
          }
        },
        {
          "t": "ητε",
          "ch": {
            "morph": "ve"
          }
        }
      ],
      "tvm": "AAS"
    },
    {
      "txt": "τὰς",
      "lem": "ὁ",
      "prs": "art acc pl fem",
      "stm": "τὰς",
      "cs": "a",
      "segs": [
        {
          "t": "τὰς",
          "ch": {
            "morph": "suf",
            "case": "a"
          }
        }
      ]
    },
    {
      "txt": "καρδίας",
      "lem": "καρδία",
      "prs": "noun acc pl fem",
      "stm": "καρδί",
      "suf": "ας",
      "cs": "a",
      "segs": [
        {
          "t": "καρδί",
          "ch": {
            "morph": "stm"
          }
        },
        {
          "t": "ας",
          "ch": {
            "morph": "suf",
            "case": "a"
          }
        }
      ]
    },
    {
      "txt": "ὑμῶν",
      "lem": "σύ",
      "prs": "pers.pron gen pl",
      "stm": "ὑμ",
      "suf": "ῶν",
      "cs": "g",
      "segs": [
        {
          "t": "ὑμ",
          "ch": {
            "morph": "stm"
          }
        },
        {
          "t": "ῶν",
          "ch": {
            "morph": "suf",
            "case": "g"
          }
        }
      ]
    },
    {
      "txt": "ὡς",
      "lem": "ὡς",
      "prs": "conj"
    },
    {
      "txt": "ἐν",
      "lem": "ἐν",
      "prs": "prep"
    },
    {
      "txt": "τῷ",
      "lem": "ὁ",
      "prs": "art dat sg masc",
      "stm": "τῷ",
      "cs": "d",
      "segs": [
        {
          "t": "τῷ",
          "ch": {
            "morph": "suf",
            "case": "d"
          }
        }
      ]
    },
    {
      "txt": "παραπικρασμῷ.",
      "lem": "παραπικρασμός",
      "prs": "noun dat sg masc",
      "stm": "παραπικρασμ",
      "suf": "ῷ",
      "cs": "d",
      "segs": [
        {
          "t": "παραπικρασμ",
          "ch": {
            "morph": "stm"
          }
        },
        {
          "t": "ῷ",
          "ch": {
            "morph": "suf",
            "case": "d"
          }
        }
      ]
    },
    {
      "br": true
    },
    {
      "v": 16
    },
    {
      "txt": "τίνες",
      "lem": "τίς",
      "prs": "inter.pron nom pl masc",
      "stm": "τίν",
      "suf": "ες",
      "cs": "n",
      "segs": [
        {
          "t": "τίν",
          "ch": {
            "morph": "stm"
          }
        },
        {
          "t": "ες",
          "ch": {
            "morph": "suf",
            "case": "n"
          }
        }
      ]
    },
    {
      "txt": "γὰρ",
      "lem": "γάρ",
      "prs": "conj"
    },
    {
      "txt": "ἀκούσαντες",
      "lem": "ἀκούω",
      "prs": "aor act ptc nom pl masc",
      "stm": "ἀκού",
      "frm": "σα",
      "ptc": "ντ",
      "suf": "ες",
      "cs": "n",
      "segs": [
        {
          "t": "ἀκού",
          "ch": {
            "morph": "stm"
          }
        },
        {
          "t": "σα",
          "ch": {
            "morph": "frm",
            "ptc": "marker"
          }
        },
        {
          "t": "ντ",
          "ch": {
            "morph": "pmk",
            "ptc": "marker"
          }
        },
        {
          "t": "ες",
          "ch": {
            "morph": "suf",
            "ptc": "marker",
            "case": "n"
          }
        }
      ],
      "tvm": "AAP"
    },
    {
      "txt": "παρεπίκραναν;",
      "lem": "παραπικραίνω",
      "prs": "aor act ind 3 pl",
      "pfx": "παρ",
      "aug": "ε",
      "stm": "πίκραν",
      "ve": "αν",
      "segs": [
        {
          "t": "παρ",
          "ch": {
            "morph": "pfx"
          }
        },
        {
          "t": "ε",
          "ch": {
            "morph": "aug"
          }
        },
        {
          "t": "πίκραν",
          "ch": {
            "morph": "stm"
          }
        },
        {
          "t": "αν",
          "ch": {
            "morph": "ve"
          }
        }
      ],
      "tvm": "AAI",
      "igl": "embittered"
    },
    {
      "br": true
    },
    {
      "txt": "ἀλλʼ",
      "lem": "ἀλλά",
      "prs": "conj"
    },
    {
      "txt": "οὐ",
      "lem": "οὐ",
      "prs": "ptcl"
    },
    {
      "txt": "πάντες",
      "lem": "πᾶς",
      "prs": "adj nom pl masc",
      "stm": "πάντ",
      "suf": "ες",
      "cs": "n",
      "segs": [
        {
          "t": "πάντ",
          "ch": {
            "morph": "stm"
          }
        },
        {
          "t": "ες",
          "ch": {
            "morph": "suf",
            "case": "n"
          }
        }
      ]
    },
    {
      "txt": "οἱ",
      "lem": "ὁ",
      "prs": "art nom pl masc",
      "stm": "οἱ",
      "cs": "n",
      "segs": [
        {
          "t": "οἱ",
          "ch": {
            "morph": "suf",
            "case": "n"
          }
        }
      ]
    },
    {
      "txt": "ἐξελθόντες",
      "lem": "ἐξέρχομαι",
      "prs": "aor act ptc nom pl masc",
      "pfx": "ἐξ",
      "stm": "ελθ",
      "ptc": "όντ",
      "suf": "ες",
      "cs": "n",
      "segs": [
        {
          "t": "ἐξ",
          "ch": {
            "morph": "pfx"
          }
        },
        {
          "t": "ελθ",
          "ch": {
            "morph": "stm"
          }
        },
        {
          "t": "όντ",
          "ch": {
            "morph": "pmk",
            "ptc": "marker"
          }
        },
        {
          "t": "ες",
          "ch": {
            "morph": "suf",
            "ptc": "marker",
            "case": "n"
          }
        }
      ],
      "tvm": "AAP"
    },
    {
      "txt": "ἐξ",
      "lem": "ἐκ",
      "prs": "prep"
    },
    {
      "txt": "Αἰγύπτου",
      "lem": "Αἴγυπτος",
      "prs": "noun gen sg fem",
      "stm": "Αἰγύπτ",
      "suf": "ου",
      "cs": "g",
      "segs": [
        {
          "t": "Αἰγύπτ",
          "ch": {
            "morph": "stm"
          }
        },
        {
          "t": "ου",
          "ch": {
            "morph": "suf",
            "case": "g"
          }
        }
      ]
    },
    {
      "txt": "διὰ",
      "lem": "διά",
      "prs": "prep"
    },
    {
      "txt": "Μωϋσέως;",
      "lem": "Μωϋσῆς",
      "prs": "noun gen sg masc",
      "stm": "Μωϋσ",
      "suf": "έως",
      "cs": "g",
      "segs": [
        {
          "t": "Μωϋσ",
          "ch": {
            "morph": "stm"
          }
        },
        {
          "t": "έως",
          "ch": {
            "morph": "suf",
            "case": "g"
          }
        }
      ]
    },
    {
      "br": true
    },
    {
      "v": 17
    },
    {
      "txt": "τίσιν",
      "lem": "τίς",
      "prs": "inter.pron dat pl masc",
      "stm": "τί",
      "suf": "σιν",
      "cs": "d",
      "segs": [
        {
          "t": "τί",
          "ch": {
            "morph": "stm"
          }
        },
        {
          "t": "σιν",
          "ch": {
            "morph": "suf",
            "case": "d"
          }
        }
      ]
    },
    {
      "txt": "δὲ",
      "lem": "δέ",
      "prs": "conj"
    },
    {
      "txt": "προσώχθισεν",
      "lem": "προσοχθίζω",
      "prs": "aor act ind 3 sg",
      "pfx": "προσ",
      "aug": "ώ",
      "stm": "χθι",
      "frm": "σε",
      "ve": "ν",
      "segs": [
        {
          "t": "προσ",
          "ch": {
            "morph": "pfx"
          }
        },
        {
          "t": "ώ",
          "ch": {
            "morph": "aug"
          }
        },
        {
          "t": "χθι",
          "ch": {
            "morph": "stm"
          }
        },
        {
          "t": "σε",
          "ch": {
            "morph": "frm"
          }
        },
        {
          "t": "ν",
          "ch": {
            "morph": "ve"
          }
        }
      ],
      "tvm": "AAI",
      "igl": "was displeased with"
    },
    {
      "txt": "τεσσεράκοντα",
      "lem": "τεσσεράκοντα",
      "prs": "adj acc pl neut",
      "stm": "τεσσεράκοντ",
      "suf": "α",
      "cs": "a",
      "segs": [
        {
          "t": "τεσσεράκοντ",
          "ch": {
            "morph": "stm"
          }
        },
        {
          "t": "α",
          "ch": {
            "morph": "suf",
            "case": "a"
          }
        }
      ]
    },
    {
      "txt": "ἔτη;",
      "lem": "ἔτος",
      "prs": "noun acc pl neut",
      "stm": "ἔτ",
      "suf": "η",
      "cs": "a",
      "segs": [
        {
          "t": "ἔτ",
          "ch": {
            "morph": "stm"
          }
        },
        {
          "t": "η",
          "ch": {
            "morph": "suf",
            "case": "a"
          }
        }
      ]
    },
    {
      "br": true
    },
    {
      "txt": "οὐχὶ",
      "lem": "οὐχί",
      "prs": "ptcl"
    },
    {
      "txt": "τοῖς",
      "lem": "ὁ",
      "prs": "art dat pl masc",
      "stm": "τοῖς",
      "cs": "d",
      "segs": [
        {
          "t": "τοῖς",
          "ch": {
            "morph": "suf",
            "case": "d"
          }
        }
      ]
    },
    {
      "txt": "ἁμαρτήσασιν,",
      "lem": "ἁμαρτάνω",
      "prs": "aor act ptc dat pl masc",
      "stm": "ἁμαρτήσ",
      "ptc": "ασι",
      "suf": "ν",
      "cs": "d",
      "segs": [
        {
          "t": "ἁμαρτήσ",
          "ch": {
            "morph": "stm"
          }
        },
        {
          "t": "ασι",
          "ch": {
            "morph": "pmk",
            "ptc": "marker"
          }
        },
        {
          "t": "ν",
          "ch": {
            "morph": "suf",
            "ptc": "marker",
            "case": "d"
          }
        }
      ],
      "tvm": "AAP"
    },
    {
      "br": true
    },
    {
      "txt": "ὧν",
      "lem": "ὅς",
      "prs": "rel.pron gen pl masc",
      "stm": "ὧν",
      "segs": [
        {
          "t": "ὧν",
          "ch": {
            "morph": "stm"
          }
        }
      ]
    },
    {
      "txt": "τὰ",
      "lem": "ὁ",
      "prs": "art nom pl neut",
      "stm": "τὰ",
      "cs": "n",
      "segs": [
        {
          "t": "τὰ",
          "ch": {
            "morph": "suf",
            "case": "n"
          }
        }
      ]
    },
    {
      "txt": "κῶλα",
      "lem": "κῶλον",
      "prs": "noun nom pl neut",
      "stm": "κῶλ",
      "suf": "α",
      "cs": "n",
      "segs": [
        {
          "t": "κῶλ",
          "ch": {
            "morph": "stm"
          }
        },
        {
          "t": "α",
          "ch": {
            "morph": "suf",
            "case": "n"
          }
        }
      ]
    },
    {
      "txt": "ἔπεσεν",
      "lem": "πίπτω",
      "prs": "aor act ind 3 sg",
      "aug": "ἔ",
      "stm": "πε",
      "frm": "σε",
      "ve": "ν",
      "segs": [
        {
          "t": "ἔ",
          "ch": {
            "morph": "aug"
          }
        },
        {
          "t": "πε",
          "ch": {
            "morph": "stm"
          }
        },
        {
          "t": "σε",
          "ch": {
            "morph": "frm"
          }
        },
        {
          "t": "ν",
          "ch": {
            "morph": "ve"
          }
        }
      ],
      "tvm": "AAI",
      "igl": "fell"
    },
    {
      "txt": "ἐν",
      "lem": "ἐν",
      "prs": "prep"
    },
    {
      "txt": "τῇ",
      "lem": "ὁ",
      "prs": "art dat sg fem",
      "stm": "τῇ",
      "cs": "d",
      "segs": [
        {
          "t": "τῇ",
          "ch": {
            "morph": "suf",
            "case": "d"
          }
        }
      ]
    },
    {
      "txt": "ἐρήμῳ;",
      "lem": "ἔρημος",
      "prs": "adj dat sg fem",
      "stm": "ἐρήμ",
      "suf": "ῳ",
      "cs": "d",
      "segs": [
        {
          "t": "ἐρήμ",
          "ch": {
            "morph": "stm"
          }
        },
        {
          "t": "ῳ",
          "ch": {
            "morph": "suf",
            "case": "d"
          }
        }
      ]
    },
    {
      "br": true
    },
    {
      "v": 18
    },
    {
      "txt": "τίσιν",
      "lem": "τίς",
      "prs": "inter.pron dat pl masc",
      "stm": "τί",
      "suf": "σιν",
      "cs": "d",
      "segs": [
        {
          "t": "τί",
          "ch": {
            "morph": "stm"
          }
        },
        {
          "t": "σιν",
          "ch": {
            "morph": "suf",
            "case": "d"
          }
        }
      ]
    },
    {
      "txt": "δὲ",
      "lem": "δέ",
      "prs": "conj"
    },
    {
      "txt": "ὤμοσεν",
      "lem": "ὀμνύω",
      "prs": "aor act ind 3 sg",
      "aug": "ὤ",
      "stm": "μο",
      "frm": "σε",
      "ve": "ν",
      "segs": [
        {
          "t": "ὤ",
          "ch": {
            "morph": "aug"
          }
        },
        {
          "t": "μο",
          "ch": {
            "morph": "stm"
          }
        },
        {
          "t": "σε",
          "ch": {
            "morph": "frm"
          }
        },
        {
          "t": "ν",
          "ch": {
            "morph": "ve"
          }
        }
      ],
      "tvm": "AAI",
      "igl": "sweared"
    },
    {
      "txt": "μὴ",
      "lem": "μή",
      "prs": "adv"
    },
    {
      "txt": "εἰσελεύσεσθαι",
      "lem": "εἰσέρχομαι",
      "prs": "fut mid inf",
      "pfx": "εἰσ",
      "stm": "ελεύ",
      "frm": "σε",
      "ve": "σθαι",
      "segs": [
        {
          "t": "εἰσ",
          "ch": {
            "morph": "pfx"
          }
        },
        {
          "t": "ελεύ",
          "ch": {
            "morph": "stm"
          }
        },
        {
          "t": "σε",
          "ch": {
            "morph": "frm"
          }
        },
        {
          "t": "σθαι",
          "ch": {
            "morph": "ve"
          }
        }
      ],
      "tvm": "FMN"
    },
    {
      "txt": "εἰς",
      "lem": "εἰς",
      "prs": "prep"
    },
    {
      "txt": "τὴν",
      "lem": "ὁ",
      "prs": "art acc sg fem",
      "stm": "τὴν",
      "cs": "a",
      "segs": [
        {
          "t": "τὴν",
          "ch": {
            "morph": "suf",
            "case": "a"
          }
        }
      ]
    },
    {
      "txt": "κατάπαυσιν",
      "lem": "κατάπαυσις",
      "prs": "noun acc sg fem",
      "stm": "κατάπαυσ",
      "suf": "ιν",
      "cs": "a",
      "segs": [
        {
          "t": "κατάπαυσ",
          "ch": {
            "morph": "stm"
          }
        },
        {
          "t": "ιν",
          "ch": {
            "morph": "suf",
            "case": "a"
          }
        }
      ]
    },
    {
      "txt": "αὐτοῦ",
      "lem": "αὐτός",
      "prs": "pers.pron gen sg masc",
      "stm": "αὐτ",
      "suf": "οῦ",
      "cs": "g",
      "segs": [
        {
          "t": "αὐτ",
          "ch": {
            "morph": "stm"
          }
        },
        {
          "t": "οῦ",
          "ch": {
            "morph": "suf",
            "case": "g"
          }
        }
      ]
    },
    {
      "br": true
    },
    {
      "txt": "εἰ",
      "lem": "εἰ",
      "prs": "conj"
    },
    {
      "txt": "μὴ",
      "lem": "μή",
      "prs": "adv"
    },
    {
      "txt": "τοῖς",
      "lem": "ὁ",
      "prs": "art dat pl masc",
      "stm": "τοῖς",
      "cs": "d",
      "segs": [
        {
          "t": "τοῖς",
          "ch": {
            "morph": "suf",
            "case": "d"
          }
        }
      ]
    },
    {
      "txt": "ἀπειθήσασιν;",
      "lem": "ἀπειθέω",
      "prs": "aor act ptc dat pl masc",
      "pfx": "ἀπ",
      "stm": "ειθή",
      "frm": "σα",
      "ptc": "σι",
      "suf": "ν",
      "cs": "d",
      "segs": [
        {
          "t": "ἀπ",
          "ch": {
            "morph": "pfx"
          }
        },
        {
          "t": "ειθή",
          "ch": {
            "morph": "stm"
          }
        },
        {
          "t": "σα",
          "ch": {
            "morph": "frm",
            "ptc": "marker"
          }
        },
        {
          "t": "σι",
          "ch": {
            "morph": "pmk",
            "ptc": "marker"
          }
        },
        {
          "t": "ν",
          "ch": {
            "morph": "suf",
            "ptc": "marker",
            "case": "d"
          }
        }
      ],
      "tvm": "AAP"
    },
    {
      "br": true
    },
    {
      "v": 19
    },
    {
      "txt": "καὶ",
      "lem": "καί",
      "prs": "conj"
    },
    {
      "txt": "βλέπομεν",
      "lem": "βλέπω",
      "prs": "pres act ind 1 pl",
      "stm": "βλέπ",
      "ve": "ομεν",
      "segs": [
        {
          "t": "βλέπ",
          "ch": {
            "morph": "stm"
          }
        },
        {
          "t": "ομεν",
          "ch": {
            "morph": "ve"
          }
        }
      ],
      "tvm": "PAI"
    },
    {
      "txt": "ὅτι",
      "lem": "ὅτι",
      "prs": "conj"
    },
    {
      "txt": "οὐκ",
      "lem": "οὐ",
      "prs": "adv"
    },
    {
      "txt": "ἠδυνήθησαν",
      "lem": "δύναμαι",
      "prs": "aor pass ind 3 pl",
      "stm": "ἠδυνή",
      "frm": "θη",
      "ve": "σαν",
      "segs": [
        {
          "t": "ἠδυνή",
          "ch": {
            "morph": "stm"
          }
        },
        {
          "t": "θη",
          "ch": {
            "morph": "frm"
          }
        },
        {
          "t": "σαν",
          "ch": {
            "morph": "ve"
          }
        }
      ],
      "tvm": "API",
      "igl": "was able"
    },
    {
      "txt": "εἰσελθεῖν",
      "lem": "εἰσέρχομαι",
      "prs": "aor act inf",
      "pfx": "εἰσ",
      "stm": "ελθ",
      "ve": "εῖν",
      "segs": [
        {
          "t": "εἰσ",
          "ch": {
            "morph": "pfx"
          }
        },
        {
          "t": "ελθ",
          "ch": {
            "morph": "stm"
          }
        },
        {
          "t": "εῖν",
          "ch": {
            "morph": "ve"
          }
        }
      ],
      "tvm": "AAN"
    },
    {
      "txt": "διʼ",
      "lem": "διά",
      "prs": "prep"
    },
    {
      "txt": "ἀπιστίαν.",
      "lem": "ἀπιστία",
      "prs": "noun acc sg fem",
      "stm": "ἀπιστί",
      "suf": "αν",
      "cs": "a",
      "segs": [
        {
          "t": "ἀπιστί",
          "ch": {
            "morph": "stm"
          }
        },
        {
          "t": "αν",
          "ch": {
            "morph": "suf",
            "case": "a"
          }
        }
      ]
    },
    {
      "br": true
    }
  ],
  "lex": {
    "ὅθεν": {
      "gl": "therefore",
      "f": 15
    },
    "ἀδελφός": {
      "gl": "brother",
      "f": 342
    },
    "ἅγιος": {
      "gl": "holy",
      "f": 233
    },
    "κλῆσις": {
      "gl": "calling",
      "f": 11
    },
    "ἐπουράνιος": {
      "gl": "heavenly",
      "f": 19
    },
    "μέτοχος": {
      "gl": "sharer",
      "f": 6
    },
    "κατανοέω": {
      "gl": "understand",
      "f": 14
    },
    "ὁ": {
      "gl": "the",
      "f": 19769
    },
    "ἀπόστολος": {
      "gl": "apostle",
      "f": 79
    },
    "καί": {
      "gl": "and",
      "f": 8973
    },
    "ἀρχιερεύς": {
      "gl": "high priest",
      "f": 122
    },
    "ὁμολογία": {
      "gl": "profession",
      "f": 6
    },
    "ἐγώ": {
      "gl": "I",
      "f": 2572
    },
    "Ἰησοῦς": {
      "gl": "Jesus",
      "f": 906
    },
    "πιστός": {
      "gl": "trustworthy",
      "f": 67
    },
    "εἰμί": {
      "gl": "be",
      "f": 2456
    },
    "ποιέω": {
      "gl": "do",
      "f": 568
    },
    "αὐτός": {
      "gl": "he",
      "f": 5546
    },
    "ὡς": {
      "gl": "as",
      "f": 503
    },
    "Μωϋσῆς": {
      "gl": "Moses",
      "f": 79
    },
    "ἐν": {
      "gl": "in",
      "f": 2733
    },
    "οἶκος": {
      "gl": "house",
      "f": 112
    },
    "πολύς": {
      "gl": "much",
      "f": 415
    },
    "γάρ": {
      "gl": "for",
      "f": 1039
    },
    "οὗτος": {
      "gl": "this",
      "f": 1385
    },
    "δόξα": {
      "gl": "glory",
      "f": 165
    },
    "παρά": {
      "gl": "from",
      "f": 193
    },
    "ἀξιόω": {
      "gl": "consider worthy",
      "f": 7
    },
    "κατά": {
      "gl": "according to",
      "f": 469
    },
    "ὅσος": {
      "gl": "how much",
      "f": 111
    },
    "τιμή": {
      "gl": "honor",
      "f": 41
    },
    "ἔχω": {
      "gl": "have",
      "f": 706
    },
    "κατασκευάζω": {
      "gl": "build",
      "f": 11
    },
    "πᾶς": {
      "gl": "all",
      "f": 1244
    },
    "ὑπό": {
      "gl": "by",
      "f": 220
    },
    "τις": {
      "gl": "any one",
      "f": 530
    },
    "δέ": {
      "gl": "but",
      "f": 2766
    },
    "θεός": {
      "gl": "God",
      "f": 1307
    },
    "μέν": {
      "gl": "indeed",
      "f": 178
    },
    "ὅλος": {
      "gl": "all",
      "f": 108
    },
    "θεράπων": {
      "gl": "servant",
      "f": 1
    },
    "εἰς": {
      "gl": "into",
      "f": 1754
    },
    "μαρτύριον": {
      "gl": "witness",
      "f": 20
    },
    "λαλέω": {
      "gl": "speak",
      "f": 297
    },
    "Χριστός": {
      "gl": "Christ",
      "f": 528
    },
    "υἱός": {
      "gl": "son",
      "f": 375
    },
    "ἐπί": {
      "gl": "upon",
      "f": 885
    },
    "ὅς": {
      "gl": "who",
      "f": 1408
    },
    "ἐάν": {
      "gl": "if",
      "f": 331
    },
    "παρρησία": {
      "gl": "freedom",
      "f": 31
    },
    "καύχημα": {
      "gl": "boasting",
      "f": 11
    },
    "ἐλπίς": {
      "gl": "hope",
      "f": 53
    },
    "κατέχω": {
      "gl": "hold fast",
      "f": 17
    },
    "διό": {
      "gl": "wherefore",
      "f": 53
    },
    "καθώς": {
      "gl": "just as",
      "f": 182
    },
    "λέγω": {
      "gl": "say",
      "f": 2345
    },
    "πνεῦμα": {
      "gl": "wind",
      "f": 379
    },
    "σήμερον": {
      "gl": "today",
      "f": 41
    },
    "φωνή": {
      "gl": "voice",
      "f": 139
    },
    "ἀκούω": {
      "gl": "hear",
      "f": 427
    },
    "μή": {
      "gl": "not",
      "f": 1036
    },
    "σκληρύνω": {
      "gl": "harden",
      "f": 6
    },
    "καρδία": {
      "gl": "heart",
      "f": 156
    },
    "σύ": {
      "gl": "you",
      "f": 2894
    },
    "παραπικρασμός": {
      "gl": "provocation",
      "f": 2
    },
    "ἡμέρα": {
      "gl": "day",
      "f": 389
    },
    "πειρασμός": {
      "gl": "temptation",
      "f": 21
    },
    "ἔρημος": {
      "gl": "deserted",
      "f": 48
    },
    "οὗ": {
      "gl": "where",
      "f": 25
    },
    "πειράζω": {
      "gl": "try",
      "f": 37
    },
    "πατήρ": {
      "gl": "father",
      "f": 413
    },
    "δοκιμασία": {
      "gl": "examination",
      "f": 1
    },
    "ὁράω": {
      "gl": "see",
      "f": 476
    },
    "ἔργον": {
      "gl": "work",
      "f": 169
    },
    "τεσσεράκοντα": {
      "gl": "forty",
      "f": 22
    },
    "ἔτος": {
      "gl": "year",
      "f": 49
    },
    "προσοχθίζω": {
      "gl": "be displeased with",
      "f": 2
    },
    "γενεά": {
      "gl": "generation",
      "f": 43
    },
    "ἀεί": {
      "gl": "always",
      "f": 7
    },
    "πλανάω": {
      "gl": "lead astray",
      "f": 39
    },
    "οὐ": {
      "gl": "no",
      "f": 1605
    },
    "γινώσκω": {
      "gl": "come to know",
      "f": 221
    },
    "ὁδός": {
      "gl": "way",
      "f": 101
    },
    "ὀμνύω": {
      "gl": "swear",
      "f": 26
    },
    "ὀργή": {
      "gl": "anger",
      "f": 36
    },
    "εἰ": {
      "gl": "if",
      "f": 502
    },
    "εἰσέρχομαι": {
      "gl": "go in",
      "f": 193
    },
    "κατάπαυσις": {
      "gl": "resting",
      "f": 9
    },
    "βλέπω": {
      "gl": "look",
      "f": 133
    },
    "μήποτε": {
      "gl": "lest at any time",
      "f": 25
    },
    "πονηρός": {
      "gl": "evil",
      "f": 78
    },
    "ἀπιστία": {
      "gl": "unbelief",
      "f": 11
    },
    "ἀφίσταμαι": {
      "gl": "lead away",
      "f": 14
    },
    "ἀπό": {
      "gl": "from",
      "f": 644
    },
    "ζάω": {
      "gl": "live",
      "f": 140
    },
    "ἀλλά": {
      "gl": "but",
      "f": 638
    },
    "παρακαλέω": {
      "gl": "urge",
      "f": 109
    },
    "ἑαυτοῦ": {
      "gl": "himself",
      "f": 333
    },
    "ἕκαστος": {
      "gl": "each",
      "f": 81
    },
    "ἄχρις": {
      "gl": "until",
      "f": 2
    },
    "καλέω": {
      "gl": "call",
      "f": 148
    },
    "ἵνα": {
      "gl": "in order that",
      "f": 662
    },
    "ἐκ": {
      "gl": "from out",
      "f": 913
    },
    "ἀπάτη": {
      "gl": "deceit",
      "f": 7
    },
    "ἁμαρτία": {
      "gl": "sin",
      "f": 172
    },
    "γίνομαι": {
      "gl": "become",
      "f": 667
    },
    "ἐάνπερ": {
      "gl": "if indeed",
      "f": 2
    },
    "ἀρχή": {
      "gl": "beginning",
      "f": 55
    },
    "ὑπόστασις": {
      "gl": "assurance",
      "f": 5
    },
    "μέχρι(ς)": {
      "gl": "as far as",
      "f": 18
    },
    "τέλος": {
      "gl": "end",
      "f": 40
    },
    "βέβαιος": {
      "gl": "firm",
      "f": 8
    },
    "τίς": {
      "gl": "who",
      "f": 554
    },
    "παραπικραίνω": {
      "gl": "embitter",
      "f": 1
    },
    "ἐξέρχομαι": {
      "gl": "go out",
      "f": 216
    },
    "Αἴγυπτος": {
      "gl": "Egypt",
      "f": 25
    },
    "διά": {
      "gl": "through",
      "f": 666
    },
    "οὐχί": {
      "gl": "by no means",
      "f": 53
    },
    "ἁμαρτάνω": {
      "gl": "sin",
      "f": 42
    },
    "κῶλον": {
      "gl": "limb",
      "f": 1
    },
    "πίπτω": {
      "gl": "fall",
      "f": 90
    },
    "ἀπειθέω": {
      "gl": "disobey",
      "f": 14
    },
    "ὅτι": {
      "gl": "that",
      "f": 1294
    },
    "δύναμαι": {
      "gl": "can",
      "f": 209
    }
  }
}